{
  "schemaVersion": "13.14.0",
  "generatedAt": "2026-07-16T14:55:36.888Z",
  "operationalStatus": "CONFIRMED_LATEST_SESSION",
  "operationalLabelAr": "قرار يومي مؤكد ومتابعة حية",
  "analysisSession": "2026-07-16",
  "marketDate": "2026-07-16",
  "marketCurrent": true,
  "analysisCurrent": true,
  "finalizationCurrent": true,
  "marketSessionState": "POST_CLOSE",
  "publicDelayedData": true,
  "liveExecutionEnabled": false,
  "automaticOrderSubmission": false,
  "finalization": {
    "status": "ALREADY_FINALIZED",
    "sessionDate": "2026-07-16",
    "coveragePct": 76.04,
    "accepted": 146,
    "eligible": 192,
    "targetPassed": true
  },
  "counts": {
    "totalCandidates": 27,
    "strict": 0,
    "tierA": 7,
    "tierB": 20,
    "ready": 7,
    "wait": 0,
    "blocked": 0,
    "unreadAlerts": 0,
    "discoveryWatch": 0
  },
  "primaryCandidate": {
    "ticker": "EEII",
    "companyNameAr": "العربية للصناعات الهندسية",
    "companyNameEn": "Arab Engineering Industries",
    "sector": "غير مصنف",
    "tier": "TIER_A_EXPERIMENTAL_PAPER",
    "tierLabelAr": "الطبقة A — ورقي تجريبي",
    "baselineRank": 2,
    "liveRank": 1,
    "rankChange": 1,
    "recommendationScore": 96.7,
    "baselineDecisionScore": 91.8,
    "liveDecisionScore": 94.4,
    "currentPrice": 2.78,
    "changePct": 1.46,
    "moveSincePreviousSnapshotPct": 0,
    "state": "ENTRY_ZONE",
    "stateLabelAr": "داخل منطقة الدخول",
    "fetchedAt": "2026-07-16T14:54:30.475Z",
    "dataAgeMinutes": 1.1,
    "stale": false,
    "marketCurrent": true,
    "plan": {
      "entryLow": 2.7673,
      "entryHigh": 2.7959,
      "stopLoss": 2.6381,
      "target1": 3.0399,
      "target2": 3.1546,
      "riskReward1": 1.8,
      "maximumHoldingSessions": 10
    },
    "support20": 2.35,
    "resistance20": 2.9,
    "rsi14": 70.33,
    "volumeRatio20": 1.204,
    "turnover": 0,
    "averageTurnover20Egp": 19139257.748,
    "turnoverPaceRatio": 0,
    "liquidityPercentile": 59.7,
    "riskScore": 67,
    "riskLabelAr": "مخاطر مرتفعة",
    "volatility20Pct": 3.139,
    "maxDrawdown100Pct": 17.647,
    "hardFailureCount": 0,
    "softFailureCount": 0,
    "softFailures": [],
    "chartPath": "../../data/quant/stocks/EEII.json",
    "latestAlerts": [
      {
        "generatedAt": "2026-07-14T08:19:25.674Z",
        "acknowledged": false,
        "id": "2026-07-14:EEII:state_change:BELOW_ENTRY",
        "level": "info",
        "type": "state_change",
        "ticker": "EEII",
        "titleAr": "EEII: أقل من منطقة الدخول",
        "detailAr": "الحالة السابقة: داخل منطقة الدخول — السعر 2.74.",
        "actionAr": "راقب اقتراب السعر من منطقة الدخول.",
        "previousValue": "ENTRY_ZONE",
        "currentValue": "BELOW_ENTRY",
        "price": 2.74,
        "tier": "TIER_B_PRIORITY_WATCH"
      },
      {
        "generatedAt": "2026-07-13T09:39:34.643Z",
        "acknowledged": false,
        "id": "2026-07-13:EEII:state_change:ENTRY_ZONE",
        "level": "opportunity",
        "type": "state_change",
        "ticker": "EEII",
        "titleAr": "EEII: داخل منطقة الدخول",
        "detailAr": "الحالة السابقة: أعلى منطقة الدخول — السعر 2.79.",
        "actionAr": "راجع الشروط والسيولة قبل تسجيل محاكاة ورقية.",
        "previousValue": "ABOVE_ENTRY",
        "currentValue": "ENTRY_ZONE",
        "price": 2.79,
        "tier": "TIER_B_PRIORITY_WATCH"
      }
    ],
    "sourceMode": "public_delayed",
    "source": "mubasher_symbol_pages",
    "finalDecision": {
      "code": "READY_FOR_PAPER_REVIEW",
      "labelAr": "جاهز للمراجعة الورقية منخفضة المخاطر",
      "actionable": true,
      "reasonAr": "السعر داخل منطقة الدخول مع بقاء طبقة التوصية صالحة."
    },
    "priorityScore": 121.44,
    "riskPct": 0.25,
    "unifiedRank": 1
  },
  "topCandidates": [
    {
      "ticker": "EEII",
      "companyNameAr": "العربية للصناعات الهندسية",
      "companyNameEn": "Arab Engineering Industries",
      "sector": "غير مصنف",
      "tier": "TIER_A_EXPERIMENTAL_PAPER",
      "tierLabelAr": "الطبقة A — ورقي تجريبي",
      "baselineRank": 2,
      "liveRank": 1,
      "rankChange": 1,
      "recommendationScore": 96.7,
      "baselineDecisionScore": 91.8,
      "liveDecisionScore": 94.4,
      "currentPrice": 2.78,
      "changePct": 1.46,
      "moveSincePreviousSnapshotPct": 0,
      "state": "ENTRY_ZONE",
      "stateLabelAr": "داخل منطقة الدخول",
      "fetchedAt": "2026-07-16T14:54:30.475Z",
      "dataAgeMinutes": 1.1,
      "stale": false,
      "marketCurrent": true,
      "plan": {
        "entryLow": 2.7673,
        "entryHigh": 2.7959,
        "stopLoss": 2.6381,
        "target1": 3.0399,
        "target2": 3.1546,
        "riskReward1": 1.8,
        "maximumHoldingSessions": 10
      },
      "support20": 2.35,
      "resistance20": 2.9,
      "rsi14": 70.33,
      "volumeRatio20": 1.204,
      "turnover": 0,
      "averageTurnover20Egp": 19139257.748,
      "turnoverPaceRatio": 0,
      "liquidityPercentile": 59.7,
      "riskScore": 67,
      "riskLabelAr": "مخاطر مرتفعة",
      "volatility20Pct": 3.139,
      "maxDrawdown100Pct": 17.647,
      "hardFailureCount": 0,
      "softFailureCount": 0,
      "softFailures": [],
      "chartPath": "../../data/quant/stocks/EEII.json",
      "latestAlerts": [
        {
          "generatedAt": "2026-07-14T08:19:25.674Z",
          "acknowledged": false,
          "id": "2026-07-14:EEII:state_change:BELOW_ENTRY",
          "level": "info",
          "type": "state_change",
          "ticker": "EEII",
          "titleAr": "EEII: أقل من منطقة الدخول",
          "detailAr": "الحالة السابقة: داخل منطقة الدخول — السعر 2.74.",
          "actionAr": "راقب اقتراب السعر من منطقة الدخول.",
          "previousValue": "ENTRY_ZONE",
          "currentValue": "BELOW_ENTRY",
          "price": 2.74,
          "tier": "TIER_B_PRIORITY_WATCH"
        },
        {
          "generatedAt": "2026-07-13T09:39:34.643Z",
          "acknowledged": false,
          "id": "2026-07-13:EEII:state_change:ENTRY_ZONE",
          "level": "opportunity",
          "type": "state_change",
          "ticker": "EEII",
          "titleAr": "EEII: داخل منطقة الدخول",
          "detailAr": "الحالة السابقة: أعلى منطقة الدخول — السعر 2.79.",
          "actionAr": "راجع الشروط والسيولة قبل تسجيل محاكاة ورقية.",
          "previousValue": "ABOVE_ENTRY",
          "currentValue": "ENTRY_ZONE",
          "price": 2.79,
          "tier": "TIER_B_PRIORITY_WATCH"
        }
      ],
      "sourceMode": "public_delayed",
      "source": "mubasher_symbol_pages",
      "finalDecision": {
        "code": "READY_FOR_PAPER_REVIEW",
        "labelAr": "جاهز للمراجعة الورقية منخفضة المخاطر",
        "actionable": true,
        "reasonAr": "السعر داخل منطقة الدخول مع بقاء طبقة التوصية صالحة."
      },
      "priorityScore": 121.44,
      "riskPct": 0.25,
      "unifiedRank": 1
    },
    {
      "ticker": "ZEOT",
      "companyNameAr": "الزيوت المستخلصة",
      "companyNameEn": "Extracted Oil & Derivatives",
      "sector": "غير مصنف",
      "tier": "TIER_A_EXPERIMENTAL_PAPER",
      "tierLabelAr": "الطبقة A — ورقي تجريبي",
      "baselineRank": 1,
      "liveRank": 2,
      "rankChange": -1,
      "recommendationScore": 97.3,
      "baselineDecisionScore": 93.2,
      "liveDecisionScore": 92,
      "currentPrice": 11.67,
      "changePct": -0.85,
      "moveSincePreviousSnapshotPct": 0,
      "state": "ENTRY_ZONE",
      "stateLabelAr": "داخل منطقة الدخول",
      "fetchedAt": "2026-07-16T14:54:30.475Z",
      "dataAgeMinutes": 1.1,
      "stale": false,
      "marketCurrent": true,
      "plan": {
        "entryLow": 11.6087,
        "entryHigh": 11.7467,
        "stopLoss": 11.0354,
        "target1": 12.8338,
        "target2": 13.3476,
        "riskReward1": 1.8,
        "maximumHoldingSessions": 10
      },
      "support20": 8.69,
      "resistance20": 12.35,
      "rsi14": 51.768,
      "volumeRatio20": 1.107,
      "turnover": 0,
      "averageTurnover20Egp": 31377144.215,
      "turnoverPaceRatio": 0,
      "liquidityPercentile": 72.3,
      "riskScore": 68,
      "riskLabelAr": "مخاطر مرتفعة",
      "volatility20Pct": 6.019,
      "maxDrawdown100Pct": 16.129,
      "hardFailureCount": 0,
      "softFailureCount": 0,
      "softFailures": [],
      "chartPath": "../../data/quant/stocks/ZEOT.json",
      "latestAlerts": [
        {
          "generatedAt": "2026-07-16T13:06:58.620Z",
          "acknowledged": false,
          "id": "2026-07-16:ZEOT:state_change:ENTRY_ZONE",
          "level": "opportunity",
          "type": "state_change",
          "ticker": "ZEOT",
          "titleAr": "ZEOT: داخل منطقة الدخول",
          "detailAr": "الحالة السابقة: أعلى منطقة الدخول — السعر 11.67.",
          "actionAr": "راجع الشروط والسيولة قبل تسجيل محاكاة ورقية.",
          "previousValue": "ABOVE_ENTRY",
          "currentValue": "ENTRY_ZONE",
          "price": 11.67,
          "tier": "TIER_A_EXPERIMENTAL_PAPER"
        },
        {
          "generatedAt": "2026-07-16T13:06:58.620Z",
          "acknowledged": false,
          "id": "2026-07-16:ZEOT:tier_change:TIER_B_PRIORITY_WATCH:TIER_A_EXPERIMENTAL_PAPER",
          "level": "opportunity",
          "type": "tier_change",
          "ticker": "ZEOT",
          "titleAr": "ZEOT: تغير مستوى الترشيح",
          "detailAr": "من الطبقة B — مراقبة أولوية إلى الطبقة A — ورقي تجريبي.",
          "actionAr": "راجع أسباب التغير في صفحة قرار اليوم.",
          "previousValue": "TIER_B_PRIORITY_WATCH",
          "currentValue": "TIER_A_EXPERIMENTAL_PAPER",
          "price": 11.67,
          "tier": "TIER_A_EXPERIMENTAL_PAPER"
        },
        {
          "generatedAt": "2026-07-16T13:06:58.620Z",
          "acknowledged": false,
          "id": "2026-07-16:ZEOT:decision_score_change:93",
          "level": "opportunity",
          "type": "decision_score_change",
          "ticker": "ZEOT",
          "titleAr": "ZEOT: تغير مهم في درجة القرار",
          "detailAr": "من 77.5 إلى 93.2.",
          "actionAr": "راجع أسباب الدرجة؛ ليست احتمال ربح.",
          "previousValue": 77.5,
          "currentValue": 93.2,
          "price": 11.67,
          "tier": "TIER_A_EXPERIMENTAL_PAPER"
        },
        {
          "generatedAt": "2026-07-15T10:16:31.517Z",
          "acknowledged": false,
          "id": "2026-07-15:ZEOT:state_change:ABOVE_ENTRY",
          "level": "info",
          "type": "state_change",
          "ticker": "ZEOT",
          "titleAr": "ZEOT: أعلى منطقة الدخول",
          "detailAr": "الحالة السابقة: داخل منطقة الدخول — السعر 11.65.",
          "actionAr": "انتظر إعادة اختبار أو خطة بديلة؛ لا تطارد السعر.",
          "previousValue": "ENTRY_ZONE",
          "currentValue": "ABOVE_ENTRY",
          "price": 11.65,
          "tier": "TIER_B_PRIORITY_WATCH"
        }
      ],
      "sourceMode": "public_delayed",
      "source": "mubasher_symbol_pages",
      "finalDecision": {
        "code": "READY_FOR_PAPER_REVIEW",
        "labelAr": "جاهز للمراجعة الورقية منخفضة المخاطر",
        "actionable": true,
        "reasonAr": "السعر داخل منطقة الدخول مع بقاء طبقة التوصية صالحة."
      },
      "priorityScore": 121.2,
      "riskPct": 0.25,
      "unifiedRank": 2
    },
    {
      "ticker": "MENA",
      "companyNameAr": "مينا للاستثمار السياحي والعقاري",
      "companyNameEn": "Mena for Touristic & Real Estate Investment",
      "sector": "غير مصنف",
      "tier": "TIER_A_EXPERIMENTAL_PAPER",
      "tierLabelAr": "الطبقة A — ورقي تجريبي",
      "baselineRank": 6,
      "liveRank": 3,
      "rankChange": 3,
      "recommendationScore": 100,
      "baselineDecisionScore": 88.8,
      "liveDecisionScore": 91.2,
      "currentPrice": 7.1,
      "changePct": 0.71,
      "moveSincePreviousSnapshotPct": 0,
      "state": "ENTRY_ZONE",
      "stateLabelAr": "داخل منطقة الدخول",
      "fetchedAt": "2026-07-16T14:54:30.475Z",
      "dataAgeMinutes": 1.1,
      "stale": false,
      "marketCurrent": true,
      "plan": {
        "entryLow": 7.0696,
        "entryHigh": 7.138,
        "stopLoss": 6.7616,
        "target1": 7.7198,
        "target2": 7.9936,
        "riskReward1": 1.8,
        "maximumHoldingSessions": 10
      },
      "support20": 6.59,
      "resistance20": 7.59,
      "rsi14": 57.5,
      "volumeRatio20": 2.037,
      "turnover": 0,
      "averageTurnover20Egp": 5824449.419,
      "turnoverPaceRatio": 0,
      "liquidityPercentile": 25.1,
      "riskScore": 66,
      "riskLabelAr": "مخاطر مرتفعة",
      "volatility20Pct": 2.963,
      "maxDrawdown100Pct": 9.607,
      "hardFailureCount": 0,
      "softFailureCount": 0,
      "softFailures": [],
      "chartPath": "../../data/quant/stocks/MENA.json",
      "latestAlerts": [
        {
          "generatedAt": "2026-07-15T08:06:24.465Z",
          "acknowledged": false,
          "id": "2026-07-15:MENA:stale_data:",
          "level": "warning",
          "type": "stale_data",
          "ticker": "MENA",
          "titleAr": "MENA: البيانات أصبحت قديمة",
          "detailAr": "عمر البيانات 15164.9 دقيقة.",
          "actionAr": "لا تعتمد على السعر حتى يصل تحديث جديد.",
          "currentValue": 15164.868116666667,
          "price": 6.89,
          "tier": null
        }
      ],
      "sourceMode": "public_delayed",
      "source": "mubasher_symbol_pages",
      "finalDecision": {
        "code": "READY_FOR_PAPER_REVIEW",
        "labelAr": "جاهز للمراجعة الورقية منخفضة المخاطر",
        "actionable": true,
        "reasonAr": "السعر داخل منطقة الدخول مع بقاء طبقة التوصية صالحة."
      },
      "priorityScore": 121.12,
      "riskPct": 0.25,
      "unifiedRank": 3
    },
    {
      "ticker": "AFDI",
      "companyNameAr": "الأهلي للتنمية والاستثمار",
      "companyNameEn": "Al Ahly for Development & Investment",
      "sector": "غير مصنف",
      "tier": "TIER_A_EXPERIMENTAL_PAPER",
      "tierLabelAr": "الطبقة A — ورقي تجريبي",
      "baselineRank": 3,
      "liveRank": 4,
      "rankChange": -1,
      "recommendationScore": 99.1,
      "baselineDecisionScore": 91,
      "liveDecisionScore": 90.5,
      "currentPrice": 47.47,
      "changePct": -0.77,
      "moveSincePreviousSnapshotPct": 0,
      "state": "ENTRY_ZONE",
      "stateLabelAr": "داخل منطقة الدخول",
      "fetchedAt": "2026-07-16T14:54:30.475Z",
      "dataAgeMinutes": 1.1,
      "stale": false,
      "marketCurrent": true,
      "plan": {
        "entryLow": 47.2427,
        "entryHigh": 47.7541,
        "stopLoss": 44.94,
        "target1": 52.1036,
        "target2": 54.1503,
        "riskReward1": 1.8,
        "maximumHoldingSessions": 10
      },
      "support20": 40.15,
      "resistance20": 48.89,
      "rsi14": 59.354,
      "volumeRatio20": 2.063,
      "turnover": 0,
      "averageTurnover20Egp": 11061657.142,
      "turnoverPaceRatio": 0,
      "liquidityPercentile": 40.8,
      "riskScore": 69,
      "riskLabelAr": "مخاطر مرتفعة",
      "volatility20Pct": 3.235,
      "maxDrawdown100Pct": 11.691,
      "hardFailureCount": 0,
      "softFailureCount": 0,
      "softFailures": [],
      "chartPath": "../../data/quant/stocks/AFDI.json",
      "latestAlerts": [
        {
          "generatedAt": "2026-07-13T12:32:10.364Z",
          "acknowledged": false,
          "id": "2026-07-13:AFDI:snapshot_move:-1:1",
          "level": "warning",
          "type": "snapshot_move",
          "ticker": "AFDI",
          "titleAr": "AFDI: هبوط 1.85% منذ آخر لقطة",
          "detailAr": "السعر السابق 47.69 والحالي 46.81.",
          "actionAr": "راجع الخطة والوقف والحجم قبل أي قرار.",
          "previousValue": 47.69,
          "currentValue": 46.81,
          "price": 46.81,
          "tier": "TIER_B_PRIORITY_WATCH"
        }
      ],
      "sourceMode": "public_delayed",
      "source": "mubasher_symbol_pages",
      "finalDecision": {
        "code": "READY_FOR_PAPER_REVIEW",
        "labelAr": "جاهز للمراجعة الورقية منخفضة المخاطر",
        "actionable": true,
        "reasonAr": "السعر داخل منطقة الدخول مع بقاء طبقة التوصية صالحة."
      },
      "priorityScore": 121.05,
      "riskPct": 0.25,
      "unifiedRank": 4
    },
    {
      "ticker": "GTWL",
      "companyNameAr": "جولدن تكس",
      "companyNameEn": "Golden Textiles & Clothes Wool",
      "sector": "غير مصنف",
      "tier": "TIER_A_EXPERIMENTAL_PAPER",
      "tierLabelAr": "الطبقة A — ورقي تجريبي",
      "baselineRank": 5,
      "liveRank": 5,
      "rankChange": 0,
      "recommendationScore": 98.7,
      "baselineDecisionScore": 89.5,
      "liveDecisionScore": 88.2,
      "currentPrice": 101.06,
      "changePct": -1.63,
      "moveSincePreviousSnapshotPct": 0,
      "state": "ENTRY_ZONE",
      "stateLabelAr": "داخل منطقة الدخول",
      "fetchedAt": "2026-07-16T14:54:30.475Z",
      "dataAgeMinutes": 1.1,
      "stale": false,
      "marketCurrent": true,
      "plan": {
        "entryLow": 100.4536,
        "entryHigh": 101.9695,
        "stopLoss": 95.645,
        "target1": 111.2315,
        "target2": 115.6848,
        "riskReward1": 1.8,
        "maximumHoldingSessions": 10
      },
      "support20": 46,
      "resistance20": 117.15,
      "rsi14": 79.365,
      "volumeRatio20": 2.183,
      "turnover": 0,
      "averageTurnover20Egp": 100062523.021,
      "turnoverPaceRatio": 0,
      "liquidityPercentile": 94.2,
      "riskScore": 70,
      "riskLabelAr": "مخاطر مرتفعة",
      "volatility20Pct": 9.349,
      "maxDrawdown100Pct": 18.2,
      "hardFailureCount": 0,
      "softFailureCount": 1,
      "softFailures": [
        {
          "id": "rsiRange",
          "labelAr": "منطقة RSI",
          "detail": 70.3,
          "classification": "soft"
        }
      ],
      "chartPath": "../../data/quant/stocks/GTWL.json",
      "latestAlerts": [],
      "sourceMode": "public_delayed",
      "source": "mubasher_symbol_pages",
      "finalDecision": {
        "code": "READY_FOR_PAPER_REVIEW",
        "labelAr": "جاهز للمراجعة الورقية منخفضة المخاطر",
        "actionable": true,
        "reasonAr": "السعر داخل منطقة الدخول مع بقاء طبقة التوصية صالحة."
      },
      "priorityScore": 120.82,
      "riskPct": 0.25,
      "unifiedRank": 5
    }
  ],
  "candidates": [
    {
      "ticker": "EEII",
      "companyNameAr": "العربية للصناعات الهندسية",
      "companyNameEn": "Arab Engineering Industries",
      "sector": "غير مصنف",
      "tier": "TIER_A_EXPERIMENTAL_PAPER",
      "tierLabelAr": "الطبقة A — ورقي تجريبي",
      "baselineRank": 2,
      "liveRank": 1,
      "rankChange": 1,
      "recommendationScore": 96.7,
      "baselineDecisionScore": 91.8,
      "liveDecisionScore": 94.4,
      "currentPrice": 2.78,
      "changePct": 1.46,
      "moveSincePreviousSnapshotPct": 0,
      "state": "ENTRY_ZONE",
      "stateLabelAr": "داخل منطقة الدخول",
      "fetchedAt": "2026-07-16T14:54:30.475Z",
      "dataAgeMinutes": 1.1,
      "stale": false,
      "marketCurrent": true,
      "plan": {
        "entryLow": 2.7673,
        "entryHigh": 2.7959,
        "stopLoss": 2.6381,
        "target1": 3.0399,
        "target2": 3.1546,
        "riskReward1": 1.8,
        "maximumHoldingSessions": 10
      },
      "support20": 2.35,
      "resistance20": 2.9,
      "rsi14": 70.33,
      "volumeRatio20": 1.204,
      "turnover": 0,
      "averageTurnover20Egp": 19139257.748,
      "turnoverPaceRatio": 0,
      "liquidityPercentile": 59.7,
      "riskScore": 67,
      "riskLabelAr": "مخاطر مرتفعة",
      "volatility20Pct": 3.139,
      "maxDrawdown100Pct": 17.647,
      "hardFailureCount": 0,
      "softFailureCount": 0,
      "softFailures": [],
      "chartPath": "../../data/quant/stocks/EEII.json",
      "latestAlerts": [
        {
          "generatedAt": "2026-07-14T08:19:25.674Z",
          "acknowledged": false,
          "id": "2026-07-14:EEII:state_change:BELOW_ENTRY",
          "level": "info",
          "type": "state_change",
          "ticker": "EEII",
          "titleAr": "EEII: أقل من منطقة الدخول",
          "detailAr": "الحالة السابقة: داخل منطقة الدخول — السعر 2.74.",
          "actionAr": "راقب اقتراب السعر من منطقة الدخول.",
          "previousValue": "ENTRY_ZONE",
          "currentValue": "BELOW_ENTRY",
          "price": 2.74,
          "tier": "TIER_B_PRIORITY_WATCH"
        },
        {
          "generatedAt": "2026-07-13T09:39:34.643Z",
          "acknowledged": false,
          "id": "2026-07-13:EEII:state_change:ENTRY_ZONE",
          "level": "opportunity",
          "type": "state_change",
          "ticker": "EEII",
          "titleAr": "EEII: داخل منطقة الدخول",
          "detailAr": "الحالة السابقة: أعلى منطقة الدخول — السعر 2.79.",
          "actionAr": "راجع الشروط والسيولة قبل تسجيل محاكاة ورقية.",
          "previousValue": "ABOVE_ENTRY",
          "currentValue": "ENTRY_ZONE",
          "price": 2.79,
          "tier": "TIER_B_PRIORITY_WATCH"
        }
      ],
      "sourceMode": "public_delayed",
      "source": "mubasher_symbol_pages",
      "finalDecision": {
        "code": "READY_FOR_PAPER_REVIEW",
        "labelAr": "جاهز للمراجعة الورقية منخفضة المخاطر",
        "actionable": true,
        "reasonAr": "السعر داخل منطقة الدخول مع بقاء طبقة التوصية صالحة."
      },
      "priorityScore": 121.44,
      "riskPct": 0.25,
      "unifiedRank": 1
    },
    {
      "ticker": "ZEOT",
      "companyNameAr": "الزيوت المستخلصة",
      "companyNameEn": "Extracted Oil & Derivatives",
      "sector": "غير مصنف",
      "tier": "TIER_A_EXPERIMENTAL_PAPER",
      "tierLabelAr": "الطبقة A — ورقي تجريبي",
      "baselineRank": 1,
      "liveRank": 2,
      "rankChange": -1,
      "recommendationScore": 97.3,
      "baselineDecisionScore": 93.2,
      "liveDecisionScore": 92,
      "currentPrice": 11.67,
      "changePct": -0.85,
      "moveSincePreviousSnapshotPct": 0,
      "state": "ENTRY_ZONE",
      "stateLabelAr": "داخل منطقة الدخول",
      "fetchedAt": "2026-07-16T14:54:30.475Z",
      "dataAgeMinutes": 1.1,
      "stale": false,
      "marketCurrent": true,
      "plan": {
        "entryLow": 11.6087,
        "entryHigh": 11.7467,
        "stopLoss": 11.0354,
        "target1": 12.8338,
        "target2": 13.3476,
        "riskReward1": 1.8,
        "maximumHoldingSessions": 10
      },
      "support20": 8.69,
      "resistance20": 12.35,
      "rsi14": 51.768,
      "volumeRatio20": 1.107,
      "turnover": 0,
      "averageTurnover20Egp": 31377144.215,
      "turnoverPaceRatio": 0,
      "liquidityPercentile": 72.3,
      "riskScore": 68,
      "riskLabelAr": "مخاطر مرتفعة",
      "volatility20Pct": 6.019,
      "maxDrawdown100Pct": 16.129,
      "hardFailureCount": 0,
      "softFailureCount": 0,
      "softFailures": [],
      "chartPath": "../../data/quant/stocks/ZEOT.json",
      "latestAlerts": [
        {
          "generatedAt": "2026-07-16T13:06:58.620Z",
          "acknowledged": false,
          "id": "2026-07-16:ZEOT:state_change:ENTRY_ZONE",
          "level": "opportunity",
          "type": "state_change",
          "ticker": "ZEOT",
          "titleAr": "ZEOT: داخل منطقة الدخول",
          "detailAr": "الحالة السابقة: أعلى منطقة الدخول — السعر 11.67.",
          "actionAr": "راجع الشروط والسيولة قبل تسجيل محاكاة ورقية.",
          "previousValue": "ABOVE_ENTRY",
          "currentValue": "ENTRY_ZONE",
          "price": 11.67,
          "tier": "TIER_A_EXPERIMENTAL_PAPER"
        },
        {
          "generatedAt": "2026-07-16T13:06:58.620Z",
          "acknowledged": false,
          "id": "2026-07-16:ZEOT:tier_change:TIER_B_PRIORITY_WATCH:TIER_A_EXPERIMENTAL_PAPER",
          "level": "opportunity",
          "type": "tier_change",
          "ticker": "ZEOT",
          "titleAr": "ZEOT: تغير مستوى الترشيح",
          "detailAr": "من الطبقة B — مراقبة أولوية إلى الطبقة A — ورقي تجريبي.",
          "actionAr": "راجع أسباب التغير في صفحة قرار اليوم.",
          "previousValue": "TIER_B_PRIORITY_WATCH",
          "currentValue": "TIER_A_EXPERIMENTAL_PAPER",
          "price": 11.67,
          "tier": "TIER_A_EXPERIMENTAL_PAPER"
        },
        {
          "generatedAt": "2026-07-16T13:06:58.620Z",
          "acknowledged": false,
          "id": "2026-07-16:ZEOT:decision_score_change:93",
          "level": "opportunity",
          "type": "decision_score_change",
          "ticker": "ZEOT",
          "titleAr": "ZEOT: تغير مهم في درجة القرار",
          "detailAr": "من 77.5 إلى 93.2.",
          "actionAr": "راجع أسباب الدرجة؛ ليست احتمال ربح.",
          "previousValue": 77.5,
          "currentValue": 93.2,
          "price": 11.67,
          "tier": "TIER_A_EXPERIMENTAL_PAPER"
        },
        {
          "generatedAt": "2026-07-15T10:16:31.517Z",
          "acknowledged": false,
          "id": "2026-07-15:ZEOT:state_change:ABOVE_ENTRY",
          "level": "info",
          "type": "state_change",
          "ticker": "ZEOT",
          "titleAr": "ZEOT: أعلى منطقة الدخول",
          "detailAr": "الحالة السابقة: داخل منطقة الدخول — السعر 11.65.",
          "actionAr": "انتظر إعادة اختبار أو خطة بديلة؛ لا تطارد السعر.",
          "previousValue": "ENTRY_ZONE",
          "currentValue": "ABOVE_ENTRY",
          "price": 11.65,
          "tier": "TIER_B_PRIORITY_WATCH"
        }
      ],
      "sourceMode": "public_delayed",
      "source": "mubasher_symbol_pages",
      "finalDecision": {
        "code": "READY_FOR_PAPER_REVIEW",
        "labelAr": "جاهز للمراجعة الورقية منخفضة المخاطر",
        "actionable": true,
        "reasonAr": "السعر داخل منطقة الدخول مع بقاء طبقة التوصية صالحة."
      },
      "priorityScore": 121.2,
      "riskPct": 0.25,
      "unifiedRank": 2
    },
    {
      "ticker": "MENA",
      "companyNameAr": "مينا للاستثمار السياحي والعقاري",
      "companyNameEn": "Mena for Touristic & Real Estate Investment",
      "sector": "غير مصنف",
      "tier": "TIER_A_EXPERIMENTAL_PAPER",
      "tierLabelAr": "الطبقة A — ورقي تجريبي",
      "baselineRank": 6,
      "liveRank": 3,
      "rankChange": 3,
      "recommendationScore": 100,
      "baselineDecisionScore": 88.8,
      "liveDecisionScore": 91.2,
      "currentPrice": 7.1,
      "changePct": 0.71,
      "moveSincePreviousSnapshotPct": 0,
      "state": "ENTRY_ZONE",
      "stateLabelAr": "داخل منطقة الدخول",
      "fetchedAt": "2026-07-16T14:54:30.475Z",
      "dataAgeMinutes": 1.1,
      "stale": false,
      "marketCurrent": true,
      "plan": {
        "entryLow": 7.0696,
        "entryHigh": 7.138,
        "stopLoss": 6.7616,
        "target1": 7.7198,
        "target2": 7.9936,
        "riskReward1": 1.8,
        "maximumHoldingSessions": 10
      },
      "support20": 6.59,
      "resistance20": 7.59,
      "rsi14": 57.5,
      "volumeRatio20": 2.037,
      "turnover": 0,
      "averageTurnover20Egp": 5824449.419,
      "turnoverPaceRatio": 0,
      "liquidityPercentile": 25.1,
      "riskScore": 66,
      "riskLabelAr": "مخاطر مرتفعة",
      "volatility20Pct": 2.963,
      "maxDrawdown100Pct": 9.607,
      "hardFailureCount": 0,
      "softFailureCount": 0,
      "softFailures": [],
      "chartPath": "../../data/quant/stocks/MENA.json",
      "latestAlerts": [
        {
          "generatedAt": "2026-07-15T08:06:24.465Z",
          "acknowledged": false,
          "id": "2026-07-15:MENA:stale_data:",
          "level": "warning",
          "type": "stale_data",
          "ticker": "MENA",
          "titleAr": "MENA: البيانات أصبحت قديمة",
          "detailAr": "عمر البيانات 15164.9 دقيقة.",
          "actionAr": "لا تعتمد على السعر حتى يصل تحديث جديد.",
          "currentValue": 15164.868116666667,
          "price": 6.89,
          "tier": null
        }
      ],
      "sourceMode": "public_delayed",
      "source": "mubasher_symbol_pages",
      "finalDecision": {
        "code": "READY_FOR_PAPER_REVIEW",
        "labelAr": "جاهز للمراجعة الورقية منخفضة المخاطر",
        "actionable": true,
        "reasonAr": "السعر داخل منطقة الدخول مع بقاء طبقة التوصية صالحة."
      },
      "priorityScore": 121.12,
      "riskPct": 0.25,
      "unifiedRank": 3
    },
    {
      "ticker": "AFDI",
      "companyNameAr": "الأهلي للتنمية والاستثمار",
      "companyNameEn": "Al Ahly for Development & Investment",
      "sector": "غير مصنف",
      "tier": "TIER_A_EXPERIMENTAL_PAPER",
      "tierLabelAr": "الطبقة A — ورقي تجريبي",
      "baselineRank": 3,
      "liveRank": 4,
      "rankChange": -1,
      "recommendationScore": 99.1,
      "baselineDecisionScore": 91,
      "liveDecisionScore": 90.5,
      "currentPrice": 47.47,
      "changePct": -0.77,
      "moveSincePreviousSnapshotPct": 0,
      "state": "ENTRY_ZONE",
      "stateLabelAr": "داخل منطقة الدخول",
      "fetchedAt": "2026-07-16T14:54:30.475Z",
      "dataAgeMinutes": 1.1,
      "stale": false,
      "marketCurrent": true,
      "plan": {
        "entryLow": 47.2427,
        "entryHigh": 47.7541,
        "stopLoss": 44.94,
        "target1": 52.1036,
        "target2": 54.1503,
        "riskReward1": 1.8,
        "maximumHoldingSessions": 10
      },
      "support20": 40.15,
      "resistance20": 48.89,
      "rsi14": 59.354,
      "volumeRatio20": 2.063,
      "turnover": 0,
      "averageTurnover20Egp": 11061657.142,
      "turnoverPaceRatio": 0,
      "liquidityPercentile": 40.8,
      "riskScore": 69,
      "riskLabelAr": "مخاطر مرتفعة",
      "volatility20Pct": 3.235,
      "maxDrawdown100Pct": 11.691,
      "hardFailureCount": 0,
      "softFailureCount": 0,
      "softFailures": [],
      "chartPath": "../../data/quant/stocks/AFDI.json",
      "latestAlerts": [
        {
          "generatedAt": "2026-07-13T12:32:10.364Z",
          "acknowledged": false,
          "id": "2026-07-13:AFDI:snapshot_move:-1:1",
          "level": "warning",
          "type": "snapshot_move",
          "ticker": "AFDI",
          "titleAr": "AFDI: هبوط 1.85% منذ آخر لقطة",
          "detailAr": "السعر السابق 47.69 والحالي 46.81.",
          "actionAr": "راجع الخطة والوقف والحجم قبل أي قرار.",
          "previousValue": 47.69,
          "currentValue": 46.81,
          "price": 46.81,
          "tier": "TIER_B_PRIORITY_WATCH"
        }
      ],
      "sourceMode": "public_delayed",
      "source": "mubasher_symbol_pages",
      "finalDecision": {
        "code": "READY_FOR_PAPER_REVIEW",
        "labelAr": "جاهز للمراجعة الورقية منخفضة المخاطر",
        "actionable": true,
        "reasonAr": "السعر داخل منطقة الدخول مع بقاء طبقة التوصية صالحة."
      },
      "priorityScore": 121.05,
      "riskPct": 0.25,
      "unifiedRank": 4
    },
    {
      "ticker": "GTWL",
      "companyNameAr": "جولدن تكس",
      "companyNameEn": "Golden Textiles & Clothes Wool",
      "sector": "غير مصنف",
      "tier": "TIER_A_EXPERIMENTAL_PAPER",
      "tierLabelAr": "الطبقة A — ورقي تجريبي",
      "baselineRank": 5,
      "liveRank": 5,
      "rankChange": 0,
      "recommendationScore": 98.7,
      "baselineDecisionScore": 89.5,
      "liveDecisionScore": 88.2,
      "currentPrice": 101.06,
      "changePct": -1.63,
      "moveSincePreviousSnapshotPct": 0,
      "state": "ENTRY_ZONE",
      "stateLabelAr": "داخل منطقة الدخول",
      "fetchedAt": "2026-07-16T14:54:30.475Z",
      "dataAgeMinutes": 1.1,
      "stale": false,
      "marketCurrent": true,
      "plan": {
        "entryLow": 100.4536,
        "entryHigh": 101.9695,
        "stopLoss": 95.645,
        "target1": 111.2315,
        "target2": 115.6848,
        "riskReward1": 1.8,
        "maximumHoldingSessions": 10
      },
      "support20": 46,
      "resistance20": 117.15,
      "rsi14": 79.365,
      "volumeRatio20": 2.183,
      "turnover": 0,
      "averageTurnover20Egp": 100062523.021,
      "turnoverPaceRatio": 0,
      "liquidityPercentile": 94.2,
      "riskScore": 70,
      "riskLabelAr": "مخاطر مرتفعة",
      "volatility20Pct": 9.349,
      "maxDrawdown100Pct": 18.2,
      "hardFailureCount": 0,
      "softFailureCount": 1,
      "softFailures": [
        {
          "id": "rsiRange",
          "labelAr": "منطقة RSI",
          "detail": 70.3,
          "classification": "soft"
        }
      ],
      "chartPath": "../../data/quant/stocks/GTWL.json",
      "latestAlerts": [],
      "sourceMode": "public_delayed",
      "source": "mubasher_symbol_pages",
      "finalDecision": {
        "code": "READY_FOR_PAPER_REVIEW",
        "labelAr": "جاهز للمراجعة الورقية منخفضة المخاطر",
        "actionable": true,
        "reasonAr": "السعر داخل منطقة الدخول مع بقاء طبقة التوصية صالحة."
      },
      "priorityScore": 120.82,
      "riskPct": 0.25,
      "unifiedRank": 5
    },
    {
      "ticker": "MCRO",
      "companyNameAr": "ماكرو جروب",
      "companyNameEn": "Macro Group Pharmaceuticals Macro Capital",
      "sector": "غير مصنف",
      "tier": "TIER_A_EXPERIMENTAL_PAPER",
      "tierLabelAr": "الطبقة A — ورقي تجريبي",
      "baselineRank": 4,
      "liveRank": 6,
      "rankChange": -2,
      "recommendationScore": 98.3,
      "baselineDecisionScore": 90.6,
      "liveDecisionScore": 88.1,
      "currentPrice": 1.33,
      "changePct": -2.21,
      "moveSincePreviousSnapshotPct": 0,
      "state": "ENTRY_ZONE",
      "stateLabelAr": "داخل منطقة الدخول",
      "fetchedAt": "2026-07-16T14:54:30.475Z",
      "dataAgeMinutes": 1.1,
      "stale": false,
      "marketCurrent": true,
      "plan": {
        "entryLow": 1.3251,
        "entryHigh": 1.3362,
        "stopLoss": 1.2752,
        "target1": 1.4304,
        "target2": 1.4747,
        "riskReward1": 1.8,
        "maximumHoldingSessions": 10
      },
      "support20": 1.17,
      "resistance20": 1.4,
      "rsi14": 66.667,
      "volumeRatio20": 0.862,
      "turnover": 0,
      "averageTurnover20Egp": 51472556.152,
      "turnoverPaceRatio": 0,
      "liquidityPercentile": 83.8,
      "riskScore": 58,
      "riskLabelAr": "مخاطر متوسطة",
      "volatility20Pct": 2.044,
      "maxDrawdown100Pct": 25.503,
      "hardFailureCount": 0,
      "softFailureCount": 1,
      "softFailures": [
        {
          "id": "volumeRatio",
          "labelAr": "دعم الحجم",
          "detail": 0.78,
          "classification": "soft"
        }
      ],
      "chartPath": "../../data/quant/stocks/MCRO.json",
      "latestAlerts": [],
      "sourceMode": "public_delayed",
      "source": "mubasher_symbol_pages",
      "finalDecision": {
        "code": "READY_FOR_PAPER_REVIEW",
        "labelAr": "جاهز للمراجعة الورقية منخفضة المخاطر",
        "actionable": true,
        "reasonAr": "السعر داخل منطقة الدخول مع بقاء طبقة التوصية صالحة."
      },
      "priorityScore": 120.81,
      "riskPct": 0.25,
      "unifiedRank": 6
    },
    {
      "ticker": "NHPS",
      "companyNameAr": "الوطنية للإسكان للنقابات المهنية",
      "companyNameEn": "National Company for Housing Professional Syndicates",
      "sector": "غير مصنف",
      "tier": "TIER_A_EXPERIMENTAL_PAPER",
      "tierLabelAr": "الطبقة A — ورقي تجريبي",
      "baselineRank": 7,
      "liveRank": 7,
      "rankChange": 0,
      "recommendationScore": 96.9,
      "baselineDecisionScore": 88.3,
      "liveDecisionScore": 86.6,
      "currentPrice": 87.11,
      "changePct": -2.14,
      "moveSincePreviousSnapshotPct": 0,
      "state": "ENTRY_ZONE",
      "stateLabelAr": "داخل منطقة الدخول",
      "fetchedAt": "2026-07-16T14:54:30.475Z",
      "dataAgeMinutes": 1.1,
      "stale": false,
      "marketCurrent": true,
      "plan": {
        "entryLow": 86.5873,
        "entryHigh": 87.8138,
        "stopLoss": 82.4046,
        "target1": 95.8335,
        "target2": 99.6703,
        "riskReward1": 1.8,
        "maximumHoldingSessions": 10
      },
      "support20": 61.55,
      "resistance20": 95,
      "rsi14": 70.988,
      "volumeRatio20": 1.778,
      "turnover": 0,
      "averageTurnover20Egp": 40989159.698,
      "turnoverPaceRatio": 0,
      "liquidityPercentile": 76.4,
      "riskScore": 71,
      "riskLabelAr": "مخاطر مرتفعة",
      "volatility20Pct": 5.389,
      "maxDrawdown100Pct": 18.866,
      "hardFailureCount": 0,
      "softFailureCount": 1,
      "softFailures": [
        {
          "id": "rsiRange",
          "labelAr": "منطقة RSI",
          "detail": 72.4,
          "classification": "soft"
        }
      ],
      "chartPath": "../../data/quant/stocks/NHPS.json",
      "latestAlerts": [],
      "sourceMode": "public_delayed",
      "source": "mubasher_symbol_pages",
      "finalDecision": {
        "code": "READY_FOR_PAPER_REVIEW",
        "labelAr": "جاهز للمراجعة الورقية منخفضة المخاطر",
        "actionable": true,
        "reasonAr": "السعر داخل منطقة الدخول مع بقاء طبقة التوصية صالحة."
      },
      "priorityScore": 120.66,
      "riskPct": 0.25,
      "unifiedRank": 7
    },
    {
      "ticker": "SCEM",
      "companyNameAr": "سيناء للأسمنت",
      "companyNameEn": "Sinai Cement",
      "sector": "غير مصنف",
      "tier": "TIER_B_PRIORITY_WATCH",
      "tierLabelAr": "الطبقة B — مراقبة أولوية",
      "baselineRank": 11,
      "liveRank": 8,
      "rankChange": 3,
      "recommendationScore": 100,
      "baselineDecisionScore": 82.2,
      "liveDecisionScore": 82.5,
      "currentPrice": 67.33,
      "changePct": 7.9,
      "moveSincePreviousSnapshotPct": 0,
      "state": "ENTRY_ZONE",
      "stateLabelAr": "داخل منطقة الدخول",
      "fetchedAt": "2026-07-16T14:54:30.475Z",
      "dataAgeMinutes": 1.1,
      "stale": false,
      "marketCurrent": true,
      "plan": {
        "entryLow": 67.1104,
        "entryHigh": 67.6046,
        "stopLoss": 64.6108,
        "target1": 72.3015,
        "target2": 74.4988,
        "riskReward1": 1.8,
        "maximumHoldingSessions": 10
      },
      "support20": 59.3,
      "resistance20": 66,
      "rsi14": 67.092,
      "volumeRatio20": 5.15,
      "turnover": 0,
      "averageTurnover20Egp": 17877614.637,
      "turnoverPaceRatio": 0,
      "liquidityPercentile": 56,
      "riskScore": 52,
      "riskLabelAr": "مخاطر متوسطة",
      "volatility20Pct": 2.375,
      "maxDrawdown100Pct": 13.135,
      "hardFailureCount": 0,
      "softFailureCount": 0,
      "softFailures": [],
      "chartPath": "../../data/quant/stocks/SCEM.json",
      "latestAlerts": [],
      "sourceMode": "public_delayed",
      "source": "mubasher_symbol_pages",
      "finalDecision": {
        "code": "WATCH_ONLY",
        "labelAr": "مراقبة فقط",
        "actionable": false,
        "reasonAr": "الطبقة B لا تتحول إلى شراء بسبب حركة لحظية."
      },
      "priorityScore": 62.25,
      "riskPct": 0.25,
      "unifiedRank": 8
    },
    {
      "ticker": "ASPI",
      "companyNameAr": "أسباير كابيتال",
      "companyNameEn": "Aspire Capital Holding for Financial Investments",
      "sector": "غير مصنف",
      "tier": "TIER_B_PRIORITY_WATCH",
      "tierLabelAr": "الطبقة B — مراقبة أولوية",
      "baselineRank": 13,
      "liveRank": 9,
      "rankChange": 4,
      "recommendationScore": 100,
      "baselineDecisionScore": 81.1,
      "liveDecisionScore": 81.8,
      "currentPrice": 0.35,
      "changePct": 11.11,
      "moveSincePreviousSnapshotPct": 0,
      "state": "ENTRY_ZONE",
      "stateLabelAr": "داخل منطقة الدخول",
      "fetchedAt": "2026-07-16T14:54:30.475Z",
      "dataAgeMinutes": 1.1,
      "stale": false,
      "marketCurrent": true,
      "plan": {
        "entryLow": 0.3483,
        "entryHigh": 0.3521,
        "stopLoss": 0.3309,
        "target1": 0.3849,
        "target2": 0.4003,
        "riskReward1": 1.8,
        "maximumHoldingSessions": 10
      },
      "support20": 0.301,
      "resistance20": 0.33,
      "rsi14": 69.048,
      "volumeRatio20": 3.787,
      "turnover": 0,
      "averageTurnover20Egp": 18244683.645,
      "turnoverPaceRatio": 0,
      "liquidityPercentile": 58.1,
      "riskScore": 69,
      "riskLabelAr": "مخاطر مرتفعة",
      "volatility20Pct": 3.42,
      "maxDrawdown100Pct": 19.947,
      "hardFailureCount": 0,
      "softFailureCount": 0,
      "softFailures": [],
      "chartPath": "../../data/quant/stocks/ASPI.json",
      "latestAlerts": [
        {
          "generatedAt": "2026-07-13T12:32:10.364Z",
          "acknowledged": false,
          "id": "2026-07-13:ASPI:state_change:BELOW_ENTRY",
          "level": "info",
          "type": "state_change",
          "ticker": "ASPI",
          "titleAr": "ASPI: أقل من منطقة الدخول",
          "detailAr": "الحالة السابقة: أعلى منطقة الدخول — السعر 0.31.",
          "actionAr": "راقب اقتراب السعر من منطقة الدخول.",
          "previousValue": "ABOVE_ENTRY",
          "currentValue": "BELOW_ENTRY",
          "price": 0.31,
          "tier": "TIER_B_PRIORITY_WATCH"
        },
        {
          "generatedAt": "2026-07-13T12:32:10.364Z",
          "acknowledged": false,
          "id": "2026-07-13:ASPI:snapshot_move:-1:2",
          "level": "warning",
          "type": "snapshot_move",
          "ticker": "ASPI",
          "titleAr": "ASPI: هبوط 3.13% منذ آخر لقطة",
          "detailAr": "السعر السابق 0.32 والحالي 0.31.",
          "actionAr": "راجع الخطة والوقف والحجم قبل أي قرار.",
          "previousValue": 0.32,
          "currentValue": 0.31,
          "price": 0.31,
          "tier": "TIER_B_PRIORITY_WATCH"
        }
      ],
      "sourceMode": "public_delayed",
      "source": "mubasher_symbol_pages",
      "finalDecision": {
        "code": "WATCH_ONLY",
        "labelAr": "مراقبة فقط",
        "actionable": false,
        "reasonAr": "الطبقة B لا تتحول إلى شراء بسبب حركة لحظية."
      },
      "priorityScore": 62.18,
      "riskPct": 0.25,
      "unifiedRank": 9
    },
    {
      "ticker": "AIFI",
      "companyNameAr": "50],[300,100],[320,100],[320,480]] End AdSlot 1 --> --> --> --> --> --> --> --> Atlas For Investment and Food Industries",
      "companyNameEn": "50], 1 Atlas For Investment and Food Industries",
      "sector": "غير مصنف",
      "tier": "TIER_B_PRIORITY_WATCH",
      "tierLabelAr": "الطبقة B — مراقبة أولوية",
      "baselineRank": 12,
      "liveRank": 10,
      "rankChange": 2,
      "recommendationScore": 99.4,
      "baselineDecisionScore": 81.6,
      "liveDecisionScore": 79.7,
      "currentPrice": 2.24,
      "changePct": 3.7,
      "moveSincePreviousSnapshotPct": 0,
      "state": "ENTRY_ZONE",
      "stateLabelAr": "داخل منطقة الدخول",
      "fetchedAt": "2026-07-16T14:54:30.475Z",
      "dataAgeMinutes": 1.1,
      "stale": false,
      "marketCurrent": true,
      "plan": {
        "entryLow": 2.232,
        "entryHigh": 2.25,
        "stopLoss": 2.1413,
        "target1": 2.4205,
        "target2": 2.5003,
        "riskReward1": 1.8,
        "maximumHoldingSessions": 10
      },
      "support20": 1.86,
      "resistance20": 2.17,
      "rsi14": 69.811,
      "volumeRatio20": 1.945,
      "turnover": 0,
      "averageTurnover20Egp": 16853554.172,
      "turnoverPaceRatio": 0,
      "liquidityPercentile": 53.4,
      "riskScore": 54,
      "riskLabelAr": "مخاطر متوسطة",
      "volatility20Pct": 1.873,
      "maxDrawdown100Pct": 21.256,
      "hardFailureCount": 0,
      "softFailureCount": 0,
      "softFailures": [],
      "chartPath": "../../data/quant/stocks/AIFI.json",
      "latestAlerts": [],
      "sourceMode": "public_delayed",
      "source": "mubasher_symbol_pages",
      "finalDecision": {
        "code": "WATCH_ONLY",
        "labelAr": "مراقبة فقط",
        "actionable": false,
        "reasonAr": "الطبقة B لا تتحول إلى شراء بسبب حركة لحظية."
      },
      "priorityScore": 61.97,
      "riskPct": 0.25,
      "unifiedRank": 10
    },
    {
      "ticker": "CSAG",
      "companyNameAr": "القناة للتوكيلات الملاحية",
      "companyNameEn": "Canal Shipping Agencies Company",
      "sector": "غير مصنف",
      "tier": "TIER_B_PRIORITY_WATCH",
      "tierLabelAr": "الطبقة B — مراقبة أولوية",
      "baselineRank": 14,
      "liveRank": 11,
      "rankChange": 3,
      "recommendationScore": 100,
      "baselineDecisionScore": 80.5,
      "liveDecisionScore": 78.8,
      "currentPrice": 33.86,
      "changePct": 3.66,
      "moveSincePreviousSnapshotPct": 0,
      "state": "ENTRY_ZONE",
      "stateLabelAr": "داخل منطقة الدخول",
      "fetchedAt": "2026-07-16T14:54:30.475Z",
      "dataAgeMinutes": 1.1,
      "stale": false,
      "marketCurrent": true,
      "plan": {
        "entryLow": 33.7756,
        "entryHigh": 33.9656,
        "stopLoss": 32.8147,
        "target1": 35.7711,
        "target2": 36.6157,
        "riskReward1": 1.8,
        "maximumHoldingSessions": 10
      },
      "support20": 30.08,
      "resistance20": 33.4,
      "rsi14": 71.537,
      "volumeRatio20": 5.382,
      "turnover": 0,
      "averageTurnover20Egp": 12019315.151,
      "turnoverPaceRatio": 0,
      "liquidityPercentile": 45,
      "riskScore": 60,
      "riskLabelAr": "مخاطر متوسطة",
      "volatility20Pct": 1.607,
      "maxDrawdown100Pct": 24.519,
      "hardFailureCount": 0,
      "softFailureCount": 0,
      "softFailures": [],
      "chartPath": "../../data/quant/stocks/CSAG.json",
      "latestAlerts": [
        {
          "generatedAt": "2026-07-15T08:06:24.465Z",
          "acknowledged": false,
          "id": "2026-07-15:CSAG:state_change:ABOVE_ENTRY",
          "level": "info",
          "type": "state_change",
          "ticker": "CSAG",
          "titleAr": "CSAG: أعلى منطقة الدخول",
          "detailAr": "الحالة السابقة: داخل منطقة الدخول — السعر 32.67.",
          "actionAr": "انتظر إعادة اختبار أو خطة بديلة؛ لا تطارد السعر.",
          "previousValue": "ENTRY_ZONE",
          "currentValue": "ABOVE_ENTRY",
          "price": 32.67,
          "tier": "TIER_B_PRIORITY_WATCH"
        }
      ],
      "sourceMode": "public_delayed",
      "source": "mubasher_symbol_pages",
      "finalDecision": {
        "code": "WATCH_ONLY",
        "labelAr": "مراقبة فقط",
        "actionable": false,
        "reasonAr": "الطبقة B لا تتحول إلى شراء بسبب حركة لحظية."
      },
      "priorityScore": 61.88,
      "riskPct": 0.25,
      "unifiedRank": 11
    },
    {
      "ticker": "ICID",
      "companyNameAr": "الدولية للاستثمار والتنمية",
      "companyNameEn": "International Co. For Investment & Development",
      "sector": "غير مصنف",
      "tier": "TIER_B_PRIORITY_WATCH",
      "tierLabelAr": "الطبقة B — مراقبة أولوية",
      "baselineRank": 23,
      "liveRank": 12,
      "rankChange": 11,
      "recommendationScore": 91.6,
      "baselineDecisionScore": 73.6,
      "liveDecisionScore": 76.5,
      "currentPrice": 8.47,
      "changePct": 6.14,
      "moveSincePreviousSnapshotPct": 0,
      "state": "ENTRY_ZONE",
      "stateLabelAr": "داخل منطقة الدخول",
      "fetchedAt": "2026-07-16T14:54:30.475Z",
      "dataAgeMinutes": 1.1,
      "stale": false,
      "marketCurrent": true,
      "plan": {
        "entryLow": 8.4192,
        "entryHigh": 8.5421,
        "stopLoss": 8.0142,
        "target1": 9.3202,
        "target2": 9.6934,
        "riskReward1": 1.8,
        "maximumHoldingSessions": 10
      },
      "support20": 6.55,
      "resistance20": 8.47,
      "rsi14": 61.386,
      "volumeRatio20": 2.397,
      "turnover": 0,
      "averageTurnover20Egp": 7008613.09,
      "turnoverPaceRatio": 0,
      "liquidityPercentile": 28.3,
      "riskScore": 69,
      "riskLabelAr": "مخاطر مرتفعة",
      "volatility20Pct": 4.126,
      "maxDrawdown100Pct": 9.669,
      "hardFailureCount": 0,
      "softFailureCount": 0,
      "softFailures": [],
      "chartPath": "../../data/quant/stocks/ICID.json",
      "latestAlerts": [
        {
          "generatedAt": "2026-07-14T10:20:15.254Z",
          "acknowledged": false,
          "id": "2026-07-14:ICID:state_change:ABOVE_ENTRY",
          "level": "info",
          "type": "state_change",
          "ticker": "ICID",
          "titleAr": "ICID: أعلى منطقة الدخول",
          "detailAr": "الحالة السابقة: أقل من منطقة الدخول — السعر 8.12.",
          "actionAr": "انتظر إعادة اختبار أو خطة بديلة؛ لا تطارد السعر.",
          "previousValue": "BELOW_ENTRY",
          "currentValue": "ABOVE_ENTRY",
          "price": 8.12,
          "tier": "TIER_B_PRIORITY_WATCH"
        },
        {
          "generatedAt": "2026-07-14T10:20:15.254Z",
          "acknowledged": false,
          "id": "2026-07-14:ICID:snapshot_move:1:1",
          "level": "opportunity",
          "type": "snapshot_move",
          "ticker": "ICID",
          "titleAr": "ICID: صعود 1.75% منذ آخر لقطة",
          "detailAr": "السعر السابق 7.98 والحالي 8.12.",
          "actionAr": "راجع الخطة والوقف والحجم قبل أي قرار.",
          "previousValue": 7.98,
          "currentValue": 8.12,
          "price": 8.12,
          "tier": "TIER_B_PRIORITY_WATCH"
        },
        {
          "generatedAt": "2026-07-14T08:19:25.674Z",
          "acknowledged": false,
          "id": "2026-07-14:ICID:state_change:BELOW_ENTRY",
          "level": "info",
          "type": "state_change",
          "ticker": "ICID",
          "titleAr": "ICID: أقل من منطقة الدخول",
          "detailAr": "الحالة السابقة: أعلى منطقة الدخول — السعر 7.98.",
          "actionAr": "راقب اقتراب السعر من منطقة الدخول.",
          "previousValue": "ABOVE_ENTRY",
          "currentValue": "BELOW_ENTRY",
          "price": 7.98,
          "tier": "TIER_B_PRIORITY_WATCH"
        },
        {
          "generatedAt": "2026-07-14T08:19:25.674Z",
          "acknowledged": false,
          "id": "2026-07-14:ICID:snapshot_move:-1:2",
          "level": "warning",
          "type": "snapshot_move",
          "ticker": "ICID",
          "titleAr": "ICID: هبوط 3.39% منذ آخر لقطة",
          "detailAr": "السعر السابق 8.26 والحالي 7.98.",
          "actionAr": "راجع الخطة والوقف والحجم قبل أي قرار.",
          "previousValue": 8.26,
          "currentValue": 7.98,
          "price": 7.98,
          "tier": "TIER_B_PRIORITY_WATCH"
        },
        {
          "generatedAt": "2026-07-14T08:19:25.674Z",
          "acknowledged": false,
          "id": "2026-07-14:ICID:session_down_cross:-3",
          "level": "warning",
          "type": "session_down_cross",
          "ticker": "ICID",
          "titleAr": "ICID: هبط دون -3% خلال الجلسة",
          "detailAr": "التغير الحالي -4.89%.",
          "actionAr": "راجع الدعم والوقف وأوقف أي دخول جديد عند كسر الخطة.",
          "currentValue": -4.89,
          "price": 7.98,
          "tier": "TIER_B_PRIORITY_WATCH"
        }
      ],
      "sourceMode": "public_delayed",
      "source": "mubasher_symbol_pages",
      "finalDecision": {
        "code": "WATCH_ONLY",
        "labelAr": "مراقبة فقط",
        "actionable": false,
        "reasonAr": "الطبقة B لا تتحول إلى شراء بسبب حركة لحظية."
      },
      "priorityScore": 61.65,
      "riskPct": 0.25,
      "unifiedRank": 12
    },
    {
      "ticker": "MASR",
      "companyNameAr": "مدينة مصر للإسكان والتعمير",
      "companyNameEn": "Madinet Masr For Housing and Development",
      "sector": "غير مصنف",
      "tier": "TIER_B_PRIORITY_WATCH",
      "tierLabelAr": "الطبقة B — مراقبة أولوية",
      "baselineRank": 8,
      "liveRank": 13,
      "rankChange": -5,
      "recommendationScore": 100,
      "baselineDecisionScore": 84,
      "liveDecisionScore": 76.2,
      "currentPrice": 8.35,
      "changePct": 0.24,
      "moveSincePreviousSnapshotPct": 0,
      "state": "ENTRY_ZONE",
      "stateLabelAr": "داخل منطقة الدخول",
      "fetchedAt": "2026-07-16T14:54:30.475Z",
      "dataAgeMinutes": 1.1,
      "stale": false,
      "marketCurrent": true,
      "plan": {
        "entryLow": 8.3172,
        "entryHigh": 8.391,
        "stopLoss": 7.9435,
        "target1": 9.0933,
        "target2": 9.4218,
        "riskReward1": 1.8,
        "maximumHoldingSessions": 10
      },
      "support20": 6.54,
      "resistance20": 8.21,
      "rsi14": 72.152,
      "volumeRatio20": 1.886,
      "turnover": 0,
      "averageTurnover20Egp": 62183896.185,
      "turnoverPaceRatio": 0,
      "liquidityPercentile": 85.3,
      "riskScore": 67,
      "riskLabelAr": "مخاطر مرتفعة",
      "volatility20Pct": 3.745,
      "maxDrawdown100Pct": 11.034,
      "hardFailureCount": 0,
      "softFailureCount": 0,
      "softFailures": [],
      "chartPath": "../../data/quant/stocks/MASR.json",
      "latestAlerts": [
        {
          "generatedAt": "2026-07-13T12:32:10.364Z",
          "acknowledged": false,
          "id": "2026-07-13:MASR:session_up_cross:3",
          "level": "opportunity",
          "type": "session_up_cross",
          "ticker": "MASR",
          "titleAr": "MASR: تجاوز +3% خلال الجلسة",
          "detailAr": "التغير الحالي 3.14%.",
          "actionAr": "راجع عدم مطاردة السعر ومساحة الهدف.",
          "currentValue": 3.14,
          "price": 8.13,
          "tier": "TIER_B_PRIORITY_WATCH"
        },
        {
          "generatedAt": "2026-07-13T09:39:34.643Z",
          "acknowledged": false,
          "id": "2026-07-13:MASR:snapshot_move:1:1",
          "level": "opportunity",
          "type": "snapshot_move",
          "ticker": "MASR",
          "titleAr": "MASR: صعود 2.52% منذ آخر لقطة",
          "detailAr": "السعر السابق 7.95 والحالي 8.15.",
          "actionAr": "راجع الخطة والوقف والحجم قبل أي قرار.",
          "previousValue": 7.95,
          "currentValue": 8.15,
          "price": 8.15,
          "tier": "TIER_B_PRIORITY_WATCH"
        }
      ],
      "sourceMode": "public_delayed",
      "source": "mubasher_symbol_pages",
      "finalDecision": {
        "code": "WATCH_ONLY",
        "labelAr": "مراقبة فقط",
        "actionable": false,
        "reasonAr": "الطبقة B لا تتحول إلى شراء بسبب حركة لحظية."
      },
      "priorityScore": 61.62,
      "riskPct": 0.25,
      "unifiedRank": 13
    },
    {
      "ticker": "EXPA",
      "companyNameAr": "البنك المصري لتنمية الصادرات",
      "companyNameEn": "Export Development Bank of Egypt",
      "sector": "غير مصنف",
      "tier": "TIER_B_PRIORITY_WATCH",
      "tierLabelAr": "الطبقة B — مراقبة أولوية",
      "baselineRank": 9,
      "liveRank": 14,
      "rankChange": -5,
      "recommendationScore": 95.9,
      "baselineDecisionScore": 83.1,
      "liveDecisionScore": 75.6,
      "currentPrice": 19.56,
      "changePct": 0.26,
      "moveSincePreviousSnapshotPct": 0,
      "state": "ENTRY_ZONE",
      "stateLabelAr": "داخل منطقة الدخول",
      "fetchedAt": "2026-07-16T14:54:30.475Z",
      "dataAgeMinutes": 1.1,
      "stale": false,
      "marketCurrent": true,
      "plan": {
        "entryLow": 19.5143,
        "entryHigh": 19.6171,
        "stopLoss": 18.9945,
        "target1": 20.5938,
        "target2": 21.0508,
        "riskReward1": 1.8,
        "maximumHoldingSessions": 10
      },
      "support20": 18.03,
      "resistance20": 19.49,
      "rsi14": 71.53,
      "volumeRatio20": 2.032,
      "turnover": 0,
      "averageTurnover20Egp": 22568906.525,
      "turnoverPaceRatio": 0,
      "liquidityPercentile": 63.9,
      "riskScore": 32,
      "riskLabelAr": "مخاطر منخفضة نسبيًا",
      "volatility20Pct": 1.112,
      "maxDrawdown100Pct": 8.309,
      "hardFailureCount": 0,
      "softFailureCount": 0,
      "softFailures": [],
      "chartPath": "../../data/quant/stocks/EXPA.json",
      "latestAlerts": [
        {
          "generatedAt": "2026-07-16T13:06:58.620Z",
          "acknowledged": false,
          "id": "2026-07-16:EXPA:state_change:ENTRY_ZONE",
          "level": "opportunity",
          "type": "state_change",
          "ticker": "EXPA",
          "titleAr": "EXPA: داخل منطقة الدخول",
          "detailAr": "الحالة السابقة: أعلى منطقة الدخول — السعر 19.56.",
          "actionAr": "راجع الشروط والسيولة قبل تسجيل محاكاة ورقية.",
          "previousValue": "ABOVE_ENTRY",
          "currentValue": "ENTRY_ZONE",
          "price": 19.56,
          "tier": "TIER_B_PRIORITY_WATCH"
        },
        {
          "generatedAt": "2026-07-15T13:47:28.332Z",
          "acknowledged": false,
          "id": "2026-07-15:EXPA:state_change:ABOVE_ENTRY",
          "level": "info",
          "type": "state_change",
          "ticker": "EXPA",
          "titleAr": "EXPA: أعلى منطقة الدخول",
          "detailAr": "الحالة السابقة: داخل منطقة الدخول — السعر 19.46.",
          "actionAr": "انتظر إعادة اختبار أو خطة بديلة؛ لا تطارد السعر.",
          "previousValue": "ENTRY_ZONE",
          "currentValue": "ABOVE_ENTRY",
          "price": 19.46,
          "tier": "TIER_B_PRIORITY_WATCH"
        },
        {
          "generatedAt": "2026-07-15T13:47:28.332Z",
          "acknowledged": false,
          "id": "2026-07-15:EXPA:snapshot_move:1:2",
          "level": "opportunity",
          "type": "snapshot_move",
          "ticker": "EXPA",
          "titleAr": "EXPA: صعود 3.02% منذ آخر لقطة",
          "detailAr": "السعر السابق 18.89 والحالي 19.46.",
          "actionAr": "راجع الخطة والوقف والحجم قبل أي قرار.",
          "previousValue": 18.89,
          "currentValue": 19.46,
          "price": 19.46,
          "tier": "TIER_B_PRIORITY_WATCH"
        },
        {
          "generatedAt": "2026-07-15T13:47:28.332Z",
          "acknowledged": false,
          "id": "2026-07-15:EXPA:session_up_cross:3",
          "level": "opportunity",
          "type": "session_up_cross",
          "ticker": "EXPA",
          "titleAr": "EXPA: تجاوز +3% خلال الجلسة",
          "detailAr": "التغير الحالي 3.13%.",
          "actionAr": "راجع عدم مطاردة السعر ومساحة الهدف.",
          "currentValue": 3.13,
          "price": 19.46,
          "tier": "TIER_B_PRIORITY_WATCH"
        }
      ],
      "sourceMode": "public_delayed",
      "source": "mubasher_symbol_pages",
      "finalDecision": {
        "code": "WATCH_ONLY",
        "labelAr": "مراقبة فقط",
        "actionable": false,
        "reasonAr": "الطبقة B لا تتحول إلى شراء بسبب حركة لحظية."
      },
      "priorityScore": 61.56,
      "riskPct": 0.25,
      "unifiedRank": 14
    },
    {
      "ticker": "NCCW",
      "companyNameAr": "النصر للأعمال المدنية",
      "companyNameEn": "Nasr Company for Civil Works",
      "sector": "غير مصنف",
      "tier": "TIER_B_PRIORITY_WATCH",
      "tierLabelAr": "الطبقة B — مراقبة أولوية",
      "baselineRank": 19,
      "liveRank": 15,
      "rankChange": 4,
      "recommendationScore": 88.9,
      "baselineDecisionScore": 77.3,
      "liveDecisionScore": 75.1,
      "currentPrice": 6.56,
      "changePct": 2.64,
      "moveSincePreviousSnapshotPct": 0,
      "state": "ENTRY_ZONE",
      "stateLabelAr": "داخل منطقة الدخول",
      "fetchedAt": "2026-07-16T14:54:30.475Z",
      "dataAgeMinutes": 1.1,
      "stale": false,
      "marketCurrent": true,
      "plan": {
        "entryLow": 6.53,
        "entryHigh": 6.5975,
        "stopLoss": 6.2256,
        "target1": 7.1723,
        "target2": 7.4428,
        "riskReward1": 1.8,
        "maximumHoldingSessions": 10
      },
      "support20": 5.82,
      "resistance20": 6.97,
      "rsi14": 55.249,
      "volumeRatio20": 1.245,
      "turnover": 0,
      "averageTurnover20Egp": 18015662.621,
      "turnoverPaceRatio": 0,
      "liquidityPercentile": 57.6,
      "riskScore": 63,
      "riskLabelAr": "مخاطر متوسطة",
      "volatility20Pct": 2.321,
      "maxDrawdown100Pct": 21.747,
      "hardFailureCount": 0,
      "softFailureCount": 0,
      "softFailures": [],
      "chartPath": "../../data/quant/stocks/NCCW.json",
      "latestAlerts": [
        {
          "generatedAt": "2026-07-16T13:06:58.620Z",
          "acknowledged": false,
          "id": "2026-07-16:NCCW:state_change:ENTRY_ZONE",
          "level": "opportunity",
          "type": "state_change",
          "ticker": "NCCW",
          "titleAr": "NCCW: داخل منطقة الدخول",
          "detailAr": "الحالة السابقة: أعلى منطقة الدخول — السعر 6.56.",
          "actionAr": "راجع الشروط والسيولة قبل تسجيل محاكاة ورقية.",
          "previousValue": "ABOVE_ENTRY",
          "currentValue": "ENTRY_ZONE",
          "price": 6.56,
          "tier": "TIER_B_PRIORITY_WATCH"
        },
        {
          "generatedAt": "2026-07-16T09:55:18.612Z",
          "acknowledged": false,
          "id": "2026-07-16:NCCW:state_change:ABOVE_ENTRY",
          "level": "info",
          "type": "state_change",
          "ticker": "NCCW",
          "titleAr": "NCCW: أعلى منطقة الدخول",
          "detailAr": "الحالة السابقة: داخل منطقة الدخول — السعر 6.55.",
          "actionAr": "انتظر إعادة اختبار أو خطة بديلة؛ لا تطارد السعر.",
          "previousValue": "ENTRY_ZONE",
          "currentValue": "ABOVE_ENTRY",
          "price": 6.55,
          "tier": "TIER_B_PRIORITY_WATCH"
        },
        {
          "generatedAt": "2026-07-16T09:55:18.612Z",
          "acknowledged": false,
          "id": "2026-07-16:NCCW:snapshot_move:1:1",
          "level": "opportunity",
          "type": "snapshot_move",
          "ticker": "NCCW",
          "titleAr": "NCCW: صعود 1.71% منذ آخر لقطة",
          "detailAr": "السعر السابق 6.44 والحالي 6.55.",
          "actionAr": "راجع الخطة والوقف والحجم قبل أي قرار.",
          "previousValue": 6.44,
          "currentValue": 6.55,
          "price": 6.55,
          "tier": "TIER_B_PRIORITY_WATCH"
        },
        {
          "generatedAt": "2026-07-15T13:47:28.332Z",
          "acknowledged": false,
          "id": "2026-07-15:NCCW:state_change:ENTRY_ZONE",
          "level": "opportunity",
          "type": "state_change",
          "ticker": "NCCW",
          "titleAr": "NCCW: داخل منطقة الدخول",
          "detailAr": "الحالة السابقة: أقل من منطقة الدخول — السعر 6.46.",
          "actionAr": "راجع الشروط والسيولة قبل تسجيل محاكاة ورقية.",
          "previousValue": "BELOW_ENTRY",
          "currentValue": "ENTRY_ZONE",
          "price": 6.46,
          "tier": "TIER_B_PRIORITY_WATCH"
        },
        {
          "generatedAt": "2026-07-15T10:16:31.517Z",
          "acknowledged": false,
          "id": "2026-07-15:NCCW:state_change:BELOW_ENTRY",
          "level": "info",
          "type": "state_change",
          "ticker": "NCCW",
          "titleAr": "NCCW: أقل من منطقة الدخول",
          "detailAr": "الحالة السابقة: داخل منطقة الدخول — السعر 6.43.",
          "actionAr": "راقب اقتراب السعر من منطقة الدخول.",
          "previousValue": "ENTRY_ZONE",
          "currentValue": "BELOW_ENTRY",
          "price": 6.43,
          "tier": "TIER_B_PRIORITY_WATCH"
        }
      ],
      "sourceMode": "public_delayed",
      "source": "mubasher_symbol_pages",
      "finalDecision": {
        "code": "WATCH_ONLY",
        "labelAr": "مراقبة فقط",
        "actionable": false,
        "reasonAr": "الطبقة B لا تتحول إلى شراء بسبب حركة لحظية."
      },
      "priorityScore": 61.51,
      "riskPct": 0.25,
      "unifiedRank": 15
    },
    {
      "ticker": "RAYA",
      "companyNameAr": "راية القابضة",
      "companyNameEn": "Raya Holding Company for Financial Investments",
      "sector": "غير مصنف",
      "tier": "TIER_B_PRIORITY_WATCH",
      "tierLabelAr": "الطبقة B — مراقبة أولوية",
      "baselineRank": 10,
      "liveRank": 16,
      "rankChange": -6,
      "recommendationScore": 96.4,
      "baselineDecisionScore": 82.6,
      "liveDecisionScore": 73.3,
      "currentPrice": 7.94,
      "changePct": -1,
      "moveSincePreviousSnapshotPct": 0,
      "state": "ENTRY_ZONE",
      "stateLabelAr": "داخل منطقة الدخول",
      "fetchedAt": "2026-07-16T14:54:30.475Z",
      "dataAgeMinutes": 1.1,
      "stale": false,
      "marketCurrent": true,
      "plan": {
        "entryLow": 7.8978,
        "entryHigh": 7.9928,
        "stopLoss": 7.5083,
        "target1": 8.7319,
        "target2": 9.0815,
        "riskReward1": 1.8,
        "maximumHoldingSessions": 10
      },
      "support20": 6.7,
      "resistance20": 8.28,
      "rsi14": 64.396,
      "volumeRatio20": 0.978,
      "turnover": 0,
      "averageTurnover20Egp": 93285741.971,
      "turnoverPaceRatio": 0,
      "liquidityPercentile": 92.7,
      "riskScore": 72,
      "riskLabelAr": "مخاطر مرتفعة",
      "volatility20Pct": 3.638,
      "maxDrawdown100Pct": 11.344,
      "hardFailureCount": 0,
      "softFailureCount": 0,
      "softFailures": [],
      "chartPath": "../../data/quant/stocks/RAYA.json",
      "latestAlerts": [
        {
          "generatedAt": "2026-07-16T13:06:58.620Z",
          "acknowledged": false,
          "id": "2026-07-16:RAYA:state_change:ENTRY_ZONE",
          "level": "opportunity",
          "type": "state_change",
          "ticker": "RAYA",
          "titleAr": "RAYA: داخل منطقة الدخول",
          "detailAr": "الحالة السابقة: أقل من منطقة الدخول — السعر 7.94.",
          "actionAr": "راجع الشروط والسيولة قبل تسجيل محاكاة ورقية.",
          "previousValue": "BELOW_ENTRY",
          "currentValue": "ENTRY_ZONE",
          "price": 7.94,
          "tier": "TIER_B_PRIORITY_WATCH"
        },
        {
          "generatedAt": "2026-07-16T09:55:18.612Z",
          "acknowledged": false,
          "id": "2026-07-16:RAYA:state_change:BELOW_ENTRY",
          "level": "info",
          "type": "state_change",
          "ticker": "RAYA",
          "titleAr": "RAYA: أقل من منطقة الدخول",
          "detailAr": "الحالة السابقة: داخل منطقة الدخول — السعر 7.9.",
          "actionAr": "راقب اقتراب السعر من منطقة الدخول.",
          "previousValue": "ENTRY_ZONE",
          "currentValue": "BELOW_ENTRY",
          "price": 7.9,
          "tier": "TIER_B_PRIORITY_WATCH"
        },
        {
          "generatedAt": "2026-07-14T08:19:25.673Z",
          "acknowledged": false,
          "id": "2026-07-14:RAYA:snapshot_move:-1:1",
          "level": "warning",
          "type": "snapshot_move",
          "ticker": "RAYA",
          "titleAr": "RAYA: هبوط 1.69% منذ آخر لقطة",
          "detailAr": "السعر السابق 8.29 والحالي 8.15.",
          "actionAr": "راجع الخطة والوقف والحجم قبل أي قرار.",
          "previousValue": 8.29,
          "currentValue": 8.15,
          "price": 8.15,
          "tier": "TIER_B_PRIORITY_WATCH"
        },
        {
          "generatedAt": "2026-07-13T12:32:10.363Z",
          "acknowledged": false,
          "id": "2026-07-13:RAYA:snapshot_move:-1:1",
          "level": "warning",
          "type": "snapshot_move",
          "ticker": "RAYA",
          "titleAr": "RAYA: هبوط 1.54% منذ آخر لقطة",
          "detailAr": "السعر السابق 8.42 والحالي 8.29.",
          "actionAr": "راجع الخطة والوقف والحجم قبل أي قرار.",
          "previousValue": 8.42,
          "currentValue": 8.29,
          "price": 8.29,
          "tier": "TIER_B_PRIORITY_WATCH"
        },
        {
          "generatedAt": "2026-07-13T09:39:34.643Z",
          "acknowledged": false,
          "id": "2026-07-13:RAYA:snapshot_move:1:1",
          "level": "opportunity",
          "type": "snapshot_move",
          "ticker": "RAYA",
          "titleAr": "RAYA: صعود 1.94% منذ آخر لقطة",
          "detailAr": "السعر السابق 8.26 والحالي 8.42.",
          "actionAr": "راجع الخطة والوقف والحجم قبل أي قرار.",
          "previousValue": 8.26,
          "currentValue": 8.42,
          "price": 8.42,
          "tier": "TIER_B_PRIORITY_WATCH"
        }
      ],
      "sourceMode": "public_delayed",
      "source": "mubasher_symbol_pages",
      "finalDecision": {
        "code": "WATCH_ONLY",
        "labelAr": "مراقبة فقط",
        "actionable": false,
        "reasonAr": "الطبقة B لا تتحول إلى شراء بسبب حركة لحظية."
      },
      "priorityScore": 61.33,
      "riskPct": 0.25,
      "unifiedRank": 16
    },
    {
      "ticker": "SEIG",
      "companyNameAr": "السعودية المصرية للاستثمار والتمويل",
      "companyNameEn": "Saudi Egyptian Investment & Finance",
      "sector": "غير مصنف",
      "tier": "TIER_B_PRIORITY_WATCH",
      "tierLabelAr": "الطبقة B — مراقبة أولوية",
      "baselineRank": 17,
      "liveRank": 17,
      "rankChange": 0,
      "recommendationScore": 95.7,
      "baselineDecisionScore": 77.7,
      "liveDecisionScore": 72.9,
      "currentPrice": 243.2,
      "changePct": 0.98,
      "moveSincePreviousSnapshotPct": 0,
      "state": "ENTRY_ZONE",
      "stateLabelAr": "داخل منطقة الدخول",
      "fetchedAt": "2026-07-16T14:54:30.475Z",
      "dataAgeMinutes": 1.1,
      "stale": false,
      "marketCurrent": true,
      "plan": {
        "entryLow": 241.7408,
        "entryHigh": 245.3875,
        "stopLoss": 230.1681,
        "target1": 267.677,
        "target2": 278.3938,
        "riskReward1": 1.8,
        "maximumHoldingSessions": 10
      },
      "support20": 180,
      "resistance20": 275,
      "rsi14": 73.046,
      "volumeRatio20": 1.119,
      "turnover": 0,
      "averageTurnover20Egp": 17809266.555,
      "turnoverPaceRatio": 0,
      "liquidityPercentile": 55.5,
      "riskScore": 72,
      "riskLabelAr": "مخاطر مرتفعة",
      "volatility20Pct": 5.62,
      "maxDrawdown100Pct": 17.697,
      "hardFailureCount": 0,
      "softFailureCount": 0,
      "softFailures": [],
      "chartPath": "../../data/quant/stocks/SEIG.json",
      "latestAlerts": [],
      "sourceMode": "public_delayed",
      "source": "mubasher_symbol_pages",
      "finalDecision": {
        "code": "WATCH_ONLY",
        "labelAr": "مراقبة فقط",
        "actionable": false,
        "reasonAr": "الطبقة B لا تتحول إلى شراء بسبب حركة لحظية."
      },
      "priorityScore": 61.29,
      "riskPct": 0.25,
      "unifiedRank": 17
    },
    {
      "ticker": "ADIB",
      "companyNameAr": "مصرف أبو ظبي الإسلامي مصر",
      "companyNameEn": "Abu Dhabi Islamic Bank Egypt",
      "sector": "غير مصنف",
      "tier": "TIER_B_PRIORITY_WATCH",
      "tierLabelAr": "الطبقة B — مراقبة أولوية",
      "baselineRank": 18,
      "liveRank": 18,
      "rankChange": 0,
      "recommendationScore": 88.7,
      "baselineDecisionScore": 77.4,
      "liveDecisionScore": 72.5,
      "currentPrice": 47,
      "changePct": 0.86,
      "moveSincePreviousSnapshotPct": 0,
      "state": "ENTRY_ZONE",
      "stateLabelAr": "داخل منطقة الدخول",
      "fetchedAt": "2026-07-16T14:54:30.475Z",
      "dataAgeMinutes": 1.1,
      "stale": false,
      "marketCurrent": true,
      "plan": {
        "entryLow": 46.8403,
        "entryHigh": 47.1996,
        "stopLoss": 45.2231,
        "target1": 50.2543,
        "target2": 51.6918,
        "riskReward1": 1.8,
        "maximumHoldingSessions": 10
      },
      "support20": 44.1,
      "resistance20": 48.49,
      "rsi14": 56.602,
      "volumeRatio20": 1.119,
      "turnover": 0,
      "averageTurnover20Egp": 79947016.833,
      "turnoverPaceRatio": 0,
      "liquidityPercentile": 90.1,
      "riskScore": 53,
      "riskLabelAr": "مخاطر متوسطة",
      "volatility20Pct": 2.2,
      "maxDrawdown100Pct": 11.765,
      "hardFailureCount": 0,
      "softFailureCount": 0,
      "softFailures": [],
      "chartPath": "../../data/quant/stocks/ADIB.json",
      "latestAlerts": [],
      "sourceMode": "public_delayed",
      "source": "mubasher_symbol_pages",
      "finalDecision": {
        "code": "WATCH_ONLY",
        "labelAr": "مراقبة فقط",
        "actionable": false,
        "reasonAr": "الطبقة B لا تتحول إلى شراء بسبب حركة لحظية."
      },
      "priorityScore": 61.25,
      "riskPct": 0.25,
      "unifiedRank": 18
    },
    {
      "ticker": "RREI",
      "companyNameAr": "العربية للاستثمارات العقارية",
      "companyNameEn": "Arab Real Estate Investment",
      "sector": "غير مصنف",
      "tier": "TIER_B_PRIORITY_WATCH",
      "tierLabelAr": "الطبقة B — مراقبة أولوية",
      "baselineRank": 16,
      "liveRank": 19,
      "rankChange": -3,
      "recommendationScore": 91.9,
      "baselineDecisionScore": 78.6,
      "liveDecisionScore": 72,
      "currentPrice": 3.93,
      "changePct": 0,
      "moveSincePreviousSnapshotPct": 0,
      "state": "ENTRY_ZONE",
      "stateLabelAr": "داخل منطقة الدخول",
      "fetchedAt": "2026-07-16T14:54:30.475Z",
      "dataAgeMinutes": 1.1,
      "stale": false,
      "marketCurrent": true,
      "plan": {
        "entryLow": 3.9131,
        "entryHigh": 3.9512,
        "stopLoss": 3.7415,
        "target1": 4.2753,
        "target2": 4.4278,
        "riskReward1": 1.8,
        "maximumHoldingSessions": 10
      },
      "support20": 3.34,
      "resistance20": 4.11,
      "rsi14": 66.667,
      "volumeRatio20": 0.992,
      "turnover": 0,
      "averageTurnover20Egp": 21958265.891,
      "turnoverPaceRatio": 0,
      "liquidityPercentile": 63.4,
      "riskScore": 64,
      "riskLabelAr": "مخاطر متوسطة",
      "volatility20Pct": 2.086,
      "maxDrawdown100Pct": 19.512,
      "hardFailureCount": 0,
      "softFailureCount": 0,
      "softFailures": [],
      "chartPath": "../../data/quant/stocks/RREI.json",
      "latestAlerts": [],
      "sourceMode": "public_delayed",
      "source": "mubasher_symbol_pages",
      "finalDecision": {
        "code": "WATCH_ONLY",
        "labelAr": "مراقبة فقط",
        "actionable": false,
        "reasonAr": "الطبقة B لا تتحول إلى شراء بسبب حركة لحظية."
      },
      "priorityScore": 61.2,
      "riskPct": 0.25,
      "unifiedRank": 19
    },
    {
      "ticker": "FAIT",
      "companyNameAr": "بنك فيصل الإسلامي",
      "companyNameEn": "Faisal Islamic Bank of Egypt",
      "sector": "غير مصنف",
      "tier": "TIER_B_PRIORITY_WATCH",
      "tierLabelAr": "الطبقة B — مراقبة أولوية",
      "baselineRank": 24,
      "liveRank": 20,
      "rankChange": 4,
      "recommendationScore": 84.3,
      "baselineDecisionScore": 72.5,
      "liveDecisionScore": 69.7,
      "currentPrice": 37.46,
      "changePct": 1.27,
      "moveSincePreviousSnapshotPct": 0,
      "state": "ENTRY_ZONE",
      "stateLabelAr": "داخل منطقة الدخول",
      "fetchedAt": "2026-07-16T14:54:30.475Z",
      "dataAgeMinutes": 1.1,
      "stale": false,
      "marketCurrent": true,
      "plan": {
        "entryLow": 37.367,
        "entryHigh": 37.5762,
        "stopLoss": 36.4255,
        "target1": 39.3546,
        "target2": 40.1915,
        "riskReward1": 1.8,
        "maximumHoldingSessions": 10
      },
      "support20": 35.06,
      "resistance20": 37.6,
      "rsi14": 62.063,
      "volumeRatio20": 1.837,
      "turnover": 0,
      "averageTurnover20Egp": 2489035.696,
      "turnoverPaceRatio": 0,
      "liquidityPercentile": 12,
      "riskScore": 44,
      "riskLabelAr": "مخاطر متوسطة",
      "volatility20Pct": 1.285,
      "maxDrawdown100Pct": 8.355,
      "hardFailureCount": 0,
      "softFailureCount": 0,
      "softFailures": [],
      "chartPath": "../../data/quant/stocks/FAIT.json",
      "latestAlerts": [
        {
          "generatedAt": "2026-07-15T08:06:24.465Z",
          "acknowledged": false,
          "id": "2026-07-15:FAIT:stale_data:",
          "level": "warning",
          "type": "stale_data",
          "ticker": "FAIT",
          "titleAr": "FAIT: البيانات أصبحت قديمة",
          "detailAr": "عمر البيانات 15191.2 دقيقة.",
          "actionAr": "لا تعتمد على السعر حتى يصل تحديث جديد.",
          "currentValue": 15191.206116666666,
          "price": 36.98,
          "tier": null
        },
        {
          "generatedAt": "2026-07-14T10:20:15.254Z",
          "acknowledged": false,
          "id": "2026-07-14:FAIT:state_change:ENTRY_ZONE",
          "level": "opportunity",
          "type": "state_change",
          "ticker": "FAIT",
          "titleAr": "FAIT: داخل منطقة الدخول",
          "detailAr": "الحالة السابقة: أعلى منطقة الدخول — السعر 37.05.",
          "actionAr": "راجع الشروط والسيولة قبل تسجيل محاكاة ورقية.",
          "previousValue": "ABOVE_ENTRY",
          "currentValue": "ENTRY_ZONE",
          "price": 37.05,
          "tier": "TIER_B_PRIORITY_WATCH"
        },
        {
          "generatedAt": "2026-07-14T08:19:25.674Z",
          "acknowledged": false,
          "id": "2026-07-14:FAIT:state_change:ABOVE_ENTRY",
          "level": "info",
          "type": "state_change",
          "ticker": "FAIT",
          "titleAr": "FAIT: أعلى منطقة الدخول",
          "detailAr": "الحالة السابقة: داخل منطقة الدخول — السعر 37.5.",
          "actionAr": "انتظر إعادة اختبار أو خطة بديلة؛ لا تطارد السعر.",
          "previousValue": "ENTRY_ZONE",
          "currentValue": "ABOVE_ENTRY",
          "price": 37.5,
          "tier": "TIER_B_PRIORITY_WATCH"
        },
        {
          "generatedAt": "2026-07-13T09:39:34.644Z",
          "acknowledged": false,
          "id": "2026-07-13:FAIT:state_change:ENTRY_ZONE",
          "level": "opportunity",
          "type": "state_change",
          "ticker": "FAIT",
          "titleAr": "FAIT: داخل منطقة الدخول",
          "detailAr": "الحالة السابقة: أعلى منطقة الدخول — السعر 37.09.",
          "actionAr": "راجع الشروط والسيولة قبل تسجيل محاكاة ورقية.",
          "previousValue": "ABOVE_ENTRY",
          "currentValue": "ENTRY_ZONE",
          "price": 37.09,
          "tier": "TIER_B_PRIORITY_WATCH"
        }
      ],
      "sourceMode": "public_delayed",
      "source": "mubasher_symbol_pages",
      "finalDecision": {
        "code": "WATCH_ONLY",
        "labelAr": "مراقبة فقط",
        "actionable": false,
        "reasonAr": "الطبقة B لا تتحول إلى شراء بسبب حركة لحظية."
      },
      "priorityScore": 60.97,
      "riskPct": 0.25,
      "unifiedRank": 20
    },
    {
      "ticker": "EGTS",
      "companyNameAr": "المصرية للمنتجعات السياحية",
      "companyNameEn": "Egyptian Resorts Company",
      "sector": "غير مصنف",
      "tier": "TIER_B_PRIORITY_WATCH",
      "tierLabelAr": "الطبقة B — مراقبة أولوية",
      "baselineRank": 20,
      "liveRank": 21,
      "rankChange": -1,
      "recommendationScore": 87.9,
      "baselineDecisionScore": 76.9,
      "liveDecisionScore": 69.6,
      "currentPrice": 18.96,
      "changePct": -0.79,
      "moveSincePreviousSnapshotPct": 0,
      "state": "ENTRY_ZONE",
      "stateLabelAr": "داخل منطقة الدخول",
      "fetchedAt": "2026-07-16T14:54:30.475Z",
      "dataAgeMinutes": 1.1,
      "stale": false,
      "marketCurrent": true,
      "plan": {
        "entryLow": 18.8462,
        "entryHigh": 19.113,
        "stopLoss": 17.9358,
        "target1": 20.8586,
        "target2": 21.6937,
        "riskReward1": 1.8,
        "maximumHoldingSessions": 10
      },
      "support20": 15.1,
      "resistance20": 19.58,
      "rsi14": 62.333,
      "volumeRatio20": 1.456,
      "turnover": 0,
      "averageTurnover20Egp": 36655667.346,
      "turnoverPaceRatio": 0,
      "liquidityPercentile": 73.8,
      "riskScore": 68,
      "riskLabelAr": "مخاطر مرتفعة",
      "volatility20Pct": 2.723,
      "maxDrawdown100Pct": 22.952,
      "hardFailureCount": 0,
      "softFailureCount": 0,
      "softFailures": [],
      "chartPath": "../../data/quant/stocks/EGTS.json",
      "latestAlerts": [],
      "sourceMode": "public_delayed",
      "source": "mubasher_symbol_pages",
      "finalDecision": {
        "code": "WATCH_ONLY",
        "labelAr": "مراقبة فقط",
        "actionable": false,
        "reasonAr": "الطبقة B لا تتحول إلى شراء بسبب حركة لحظية."
      },
      "priorityScore": 60.96,
      "riskPct": 0.25,
      "unifiedRank": 21
    },
    {
      "ticker": "ELWA",
      "companyNameAr": "الوادي العالمية للاستثمار والتنمية",
      "companyNameEn": "El Wadi for International and Investment Development",
      "sector": "غير مصنف",
      "tier": "TIER_B_PRIORITY_WATCH",
      "tierLabelAr": "الطبقة B — مراقبة أولوية",
      "baselineRank": 25,
      "liveRank": 22,
      "rankChange": 3,
      "recommendationScore": 85,
      "baselineDecisionScore": 71.9,
      "liveDecisionScore": 68.1,
      "currentPrice": 2.04,
      "changePct": 0.49,
      "moveSincePreviousSnapshotPct": 0,
      "state": "ENTRY_ZONE",
      "stateLabelAr": "داخل منطقة الدخول",
      "fetchedAt": "2026-07-16T14:54:30.475Z",
      "dataAgeMinutes": 1.1,
      "stale": false,
      "marketCurrent": true,
      "plan": {
        "entryLow": 2.0303,
        "entryHigh": 2.0521,
        "stopLoss": 1.9325,
        "target1": 2.2368,
        "target2": 2.3238,
        "riskReward1": 1.8,
        "maximumHoldingSessions": 10
      },
      "support20": 1.87,
      "resistance20": 2.14,
      "rsi14": 50,
      "volumeRatio20": 0.884,
      "turnover": 0,
      "averageTurnover20Egp": 1133456.407,
      "turnoverPaceRatio": 0,
      "liquidityPercentile": 10.5,
      "riskScore": 49,
      "riskLabelAr": "مخاطر متوسطة",
      "volatility20Pct": 1.742,
      "maxDrawdown100Pct": 10.698,
      "hardFailureCount": 0,
      "softFailureCount": 0,
      "softFailures": [],
      "chartPath": "../../data/quant/stocks/ELWA.json",
      "latestAlerts": [
        {
          "generatedAt": "2026-07-16T07:53:24.829Z",
          "acknowledged": false,
          "id": "2026-07-16:ELWA:stale_data:",
          "level": "warning",
          "type": "stale_data",
          "ticker": "ELWA",
          "titleAr": "ELWA: البيانات أصبحت قديمة",
          "detailAr": "عمر البيانات 16642.6 دقيقة.",
          "actionAr": "لا تعتمد على السعر حتى يصل تحديث جديد.",
          "currentValue": 16642.57435,
          "price": 1.95,
          "tier": null
        },
        {
          "generatedAt": "2026-07-14T08:19:25.674Z",
          "acknowledged": false,
          "id": "2026-07-14:ELWA:stale_data:",
          "level": "warning",
          "type": "stale_data",
          "ticker": "ELWA",
          "titleAr": "ELWA: البيانات أصبحت قديمة",
          "detailAr": "عمر البيانات 13788.6 دقيقة.",
          "actionAr": "لا تعتمد على السعر حتى يصل تحديث جديد.",
          "currentValue": 13788.588283333333,
          "price": 1.95,
          "tier": null
        }
      ],
      "sourceMode": "public_delayed",
      "source": "mubasher_symbol_pages",
      "finalDecision": {
        "code": "WATCH_ONLY",
        "labelAr": "مراقبة فقط",
        "actionable": false,
        "reasonAr": "الطبقة B لا تتحول إلى شراء بسبب حركة لحظية."
      },
      "priorityScore": 60.81,
      "riskPct": 0.25,
      "unifiedRank": 22
    },
    {
      "ticker": "RACC",
      "companyNameAr": "راية لخدمات مراكز الاتصالات",
      "companyNameEn": "Raya Customer Experience",
      "sector": "غير مصنف",
      "tier": "TIER_B_PRIORITY_WATCH",
      "tierLabelAr": "الطبقة B — مراقبة أولوية",
      "baselineRank": 21,
      "liveRank": 23,
      "rankChange": -2,
      "recommendationScore": 89.5,
      "baselineDecisionScore": 76.6,
      "liveDecisionScore": 68,
      "currentPrice": 10.18,
      "changePct": -1.74,
      "moveSincePreviousSnapshotPct": 0,
      "state": "ENTRY_ZONE",
      "stateLabelAr": "داخل منطقة الدخول",
      "fetchedAt": "2026-07-16T14:54:30.475Z",
      "dataAgeMinutes": 1.1,
      "stale": false,
      "marketCurrent": true,
      "plan": {
        "entryLow": 10.1447,
        "entryHigh": 10.2241,
        "stopLoss": 9.7875,
        "target1": 10.8989,
        "target2": 11.2165,
        "riskReward1": 1.8,
        "maximumHoldingSessions": 10
      },
      "support20": 9.36,
      "resistance20": 10.57,
      "rsi14": 61.29,
      "volumeRatio20": 2.378,
      "turnover": 0,
      "averageTurnover20Egp": 9406782.391,
      "turnoverPaceRatio": 0,
      "liquidityPercentile": 35.1,
      "riskScore": 47,
      "riskLabelAr": "مخاطر متوسطة",
      "volatility20Pct": 1.715,
      "maxDrawdown100Pct": 10,
      "hardFailureCount": 0,
      "softFailureCount": 0,
      "softFailures": [],
      "chartPath": "../../data/quant/stocks/RACC.json",
      "latestAlerts": [
        {
          "generatedAt": "2026-07-16T11:28:47.100Z",
          "acknowledged": false,
          "id": "2026-07-16:RACC:state_change:BELOW_ENTRY",
          "level": "info",
          "type": "state_change",
          "ticker": "RACC",
          "titleAr": "RACC: أقل من منطقة الدخول",
          "detailAr": "الحالة السابقة: داخل منطقة الدخول — السعر 10.15.",
          "actionAr": "راقب اقتراب السعر من منطقة الدخول.",
          "previousValue": "ENTRY_ZONE",
          "currentValue": "BELOW_ENTRY",
          "price": 10.15,
          "tier": "TIER_B_PRIORITY_WATCH"
        },
        {
          "generatedAt": "2026-07-16T11:28:47.100Z",
          "acknowledged": false,
          "id": "2026-07-16:RACC:snapshot_move:-1:1",
          "level": "warning",
          "type": "snapshot_move",
          "ticker": "RACC",
          "titleAr": "RACC: هبوط 1.74% منذ آخر لقطة",
          "detailAr": "السعر السابق 10.33 والحالي 10.15.",
          "actionAr": "راجع الخطة والوقف والحجم قبل أي قرار.",
          "previousValue": 10.33,
          "currentValue": 10.15,
          "price": 10.15,
          "tier": "TIER_B_PRIORITY_WATCH"
        },
        {
          "generatedAt": "2026-07-16T09:55:18.612Z",
          "acknowledged": false,
          "id": "2026-07-16:RACC:state_change:ENTRY_ZONE",
          "level": "opportunity",
          "type": "state_change",
          "ticker": "RACC",
          "titleAr": "RACC: داخل منطقة الدخول",
          "detailAr": "الحالة السابقة: أعلى منطقة الدخول — السعر 10.33.",
          "actionAr": "راجع الشروط والسيولة قبل تسجيل محاكاة ورقية.",
          "previousValue": "ABOVE_ENTRY",
          "currentValue": "ENTRY_ZONE",
          "price": 10.33,
          "tier": "TIER_B_PRIORITY_WATCH"
        },
        {
          "generatedAt": "2026-07-16T07:53:24.829Z",
          "acknowledged": false,
          "id": "2026-07-16:RACC:state_change:ABOVE_ENTRY",
          "level": "info",
          "type": "state_change",
          "ticker": "RACC",
          "titleAr": "RACC: أعلى منطقة الدخول",
          "detailAr": "الحالة السابقة: داخل منطقة الدخول — السعر 10.4.",
          "actionAr": "انتظر إعادة اختبار أو خطة بديلة؛ لا تطارد السعر.",
          "previousValue": "ENTRY_ZONE",
          "currentValue": "ABOVE_ENTRY",
          "price": 10.4,
          "tier": "TIER_B_PRIORITY_WATCH"
        }
      ],
      "sourceMode": "public_delayed",
      "source": "mubasher_symbol_pages",
      "finalDecision": {
        "code": "WATCH_ONLY",
        "labelAr": "مراقبة فقط",
        "actionable": false,
        "reasonAr": "الطبقة B لا تتحول إلى شراء بسبب حركة لحظية."
      },
      "priorityScore": 60.8,
      "riskPct": 0.25,
      "unifiedRank": 23
    },
    {
      "ticker": "DAPH",
      "companyNameAr": "المشروعات الصناعية والهندسية",
      "companyNameEn": "Development & Engineering Consultants",
      "sector": "غير مصنف",
      "tier": "TIER_B_PRIORITY_WATCH",
      "tierLabelAr": "الطبقة B — مراقبة أولوية",
      "baselineRank": 22,
      "liveRank": 24,
      "rankChange": -2,
      "recommendationScore": 90.9,
      "baselineDecisionScore": 75.4,
      "liveDecisionScore": 68,
      "currentPrice": 86.27,
      "changePct": -1.18,
      "moveSincePreviousSnapshotPct": 0,
      "state": "ENTRY_ZONE",
      "stateLabelAr": "داخل منطقة الدخول",
      "fetchedAt": "2026-07-16T14:54:30.475Z",
      "dataAgeMinutes": 1.1,
      "stale": false,
      "marketCurrent": true,
      "plan": {
        "entryLow": 85.9573,
        "entryHigh": 86.6608,
        "stopLoss": 82.79,
        "target1": 92.6434,
        "target2": 95.4587,
        "riskReward1": 1.8,
        "maximumHoldingSessions": 10
      },
      "support20": 77.52,
      "resistance20": 87.9,
      "rsi14": 64.648,
      "volumeRatio20": 1.148,
      "turnover": 0,
      "averageTurnover20Egp": 8394664.831,
      "turnoverPaceRatio": 0,
      "liquidityPercentile": 30.9,
      "riskScore": 59,
      "riskLabelAr": "مخاطر متوسطة",
      "volatility20Pct": 2.023,
      "maxDrawdown100Pct": 18.685,
      "hardFailureCount": 0,
      "softFailureCount": 0,
      "softFailures": [],
      "chartPath": "../../data/quant/stocks/DAPH.json",
      "latestAlerts": [],
      "sourceMode": "public_delayed",
      "source": "mubasher_symbol_pages",
      "finalDecision": {
        "code": "WATCH_ONLY",
        "labelAr": "مراقبة فقط",
        "actionable": false,
        "reasonAr": "الطبقة B لا تتحول إلى شراء بسبب حركة لحظية."
      },
      "priorityScore": 60.8,
      "riskPct": 0.25,
      "unifiedRank": 24
    },
    {
      "ticker": "MIPH",
      "companyNameAr": "مينا فارم",
      "companyNameEn": "MINAPHARM Pharmaceuticals",
      "sector": "غير مصنف",
      "tier": "TIER_B_PRIORITY_WATCH",
      "tierLabelAr": "الطبقة B — مراقبة أولوية",
      "baselineRank": 26,
      "liveRank": 25,
      "rankChange": 1,
      "recommendationScore": 86.1,
      "baselineDecisionScore": 70,
      "liveDecisionScore": 67.6,
      "currentPrice": 760,
      "changePct": 1.04,
      "moveSincePreviousSnapshotPct": 0,
      "state": "ENTRY_ZONE",
      "stateLabelAr": "داخل منطقة الدخول",
      "fetchedAt": "2026-07-16T14:54:30.475Z",
      "dataAgeMinutes": 1.1,
      "stale": false,
      "marketCurrent": true,
      "plan": {
        "entryLow": 757.0402,
        "entryHigh": 763.6997,
        "stopLoss": 723.3546,
        "target1": 826.9977,
        "target2": 856.61,
        "riskReward1": 1.8,
        "maximumHoldingSessions": 10
      },
      "support20": 630.13,
      "resistance20": 760,
      "rsi14": 78.811,
      "volumeRatio20": 1.95,
      "turnover": 0,
      "averageTurnover20Egp": 3163743.914,
      "turnoverPaceRatio": 0,
      "liquidityPercentile": 13.6,
      "riskScore": 66,
      "riskLabelAr": "مخاطر مرتفعة",
      "volatility20Pct": 2.365,
      "maxDrawdown100Pct": 11.692,
      "hardFailureCount": 0,
      "softFailureCount": 0,
      "softFailures": [],
      "chartPath": "../../data/quant/stocks/MIPH.json",
      "latestAlerts": [
        {
          "generatedAt": "2026-07-16T13:06:58.620Z",
          "acknowledged": false,
          "id": "2026-07-16:MIPH:state_change:ENTRY_ZONE",
          "level": "opportunity",
          "type": "state_change",
          "ticker": "MIPH",
          "titleAr": "MIPH: داخل منطقة الدخول",
          "detailAr": "الحالة السابقة: أعلى منطقة الدخول — السعر 760.",
          "actionAr": "راجع الشروط والسيولة قبل تسجيل محاكاة ورقية.",
          "previousValue": "ABOVE_ENTRY",
          "currentValue": "ENTRY_ZONE",
          "price": 760,
          "tier": "TIER_B_PRIORITY_WATCH"
        },
        {
          "generatedAt": "2026-07-16T13:06:58.620Z",
          "acknowledged": false,
          "id": "2026-07-16:MIPH:tier_change:TIER_A_EXPERIMENTAL_PAPER:TIER_B_PRIORITY_WATCH",
          "level": "opportunity",
          "type": "tier_change",
          "ticker": "MIPH",
          "titleAr": "MIPH: تغير مستوى الترشيح",
          "detailAr": "من الطبقة A — ورقي تجريبي إلى الطبقة B — مراقبة أولوية.",
          "actionAr": "راجع أسباب التغير في صفحة قرار اليوم.",
          "previousValue": "TIER_A_EXPERIMENTAL_PAPER",
          "currentValue": "TIER_B_PRIORITY_WATCH",
          "price": 760,
          "tier": "TIER_B_PRIORITY_WATCH"
        },
        {
          "generatedAt": "2026-07-16T13:06:58.620Z",
          "acknowledged": false,
          "id": "2026-07-16:MIPH:decision_score_change:70",
          "level": "warning",
          "type": "decision_score_change",
          "ticker": "MIPH",
          "titleAr": "MIPH: تغير مهم في درجة القرار",
          "detailAr": "من 88.7 إلى 70.",
          "actionAr": "راجع أسباب الدرجة؛ ليست احتمال ربح.",
          "previousValue": 88.7,
          "currentValue": 70,
          "price": 760,
          "tier": "TIER_B_PRIORITY_WATCH"
        },
        {
          "generatedAt": "2026-07-16T09:55:18.611Z",
          "acknowledged": false,
          "id": "2026-07-16:MIPH:snapshot_move:1:1",
          "level": "opportunity",
          "type": "snapshot_move",
          "ticker": "MIPH",
          "titleAr": "MIPH: صعود 2.5% منذ آخر لقطة",
          "detailAr": "السعر السابق 740.35 والحالي 758.84.",
          "actionAr": "راجع الخطة والوقف والحجم قبل أي قرار.",
          "previousValue": 740.35,
          "currentValue": 758.84,
          "price": 758.84,
          "tier": "TIER_A_EXPERIMENTAL_PAPER"
        },
        {
          "generatedAt": "2026-07-16T07:53:24.829Z",
          "acknowledged": false,
          "id": "2026-07-16:MIPH:snapshot_move:-1:1",
          "level": "warning",
          "type": "snapshot_move",
          "ticker": "MIPH",
          "titleAr": "MIPH: هبوط 1.57% منذ آخر لقطة",
          "detailAr": "السعر السابق 752.17 والحالي 740.35.",
          "actionAr": "راجع الخطة والوقف والحجم قبل أي قرار.",
          "previousValue": 752.17,
          "currentValue": 740.35,
          "price": 740.35,
          "tier": "TIER_A_EXPERIMENTAL_PAPER"
        }
      ],
      "sourceMode": "public_delayed",
      "source": "mubasher_symbol_pages",
      "finalDecision": {
        "code": "WATCH_ONLY",
        "labelAr": "مراقبة فقط",
        "actionable": false,
        "reasonAr": "الطبقة B لا تتحول إلى شراء بسبب حركة لحظية."
      },
      "priorityScore": 60.76,
      "riskPct": 0.25,
      "unifiedRank": 25
    },
    {
      "ticker": "GIHD",
      "companyNameAr": "الغربية الإسلامية للتنمية العمرانية",
      "companyNameEn": "Gharbia Islamic Housing Development",
      "sector": "غير مصنف",
      "tier": "TIER_B_PRIORITY_WATCH",
      "tierLabelAr": "الطبقة B — مراقبة أولوية",
      "baselineRank": 15,
      "liveRank": 26,
      "rankChange": -11,
      "recommendationScore": 94.4,
      "baselineDecisionScore": 78.7,
      "liveDecisionScore": 66.7,
      "currentPrice": 50.25,
      "changePct": -3.57,
      "moveSincePreviousSnapshotPct": 0,
      "state": "ENTRY_ZONE",
      "stateLabelAr": "داخل منطقة الدخول",
      "fetchedAt": "2026-07-16T14:54:30.475Z",
      "dataAgeMinutes": 1.1,
      "stale": false,
      "marketCurrent": true,
      "plan": {
        "entryLow": 49.9485,
        "entryHigh": 50.6442,
        "stopLoss": 47.5301,
        "target1": 55.2757,
        "target2": 57.4887,
        "riskReward1": 1.8,
        "maximumHoldingSessions": 10
      },
      "support20": 35.15,
      "resistance20": 52.4,
      "rsi14": 68.357,
      "volumeRatio20": 1.168,
      "turnover": 0,
      "averageTurnover20Egp": 24230043.47,
      "turnoverPaceRatio": 0,
      "liquidityPercentile": 65.4,
      "riskScore": 78,
      "riskLabelAr": "مخاطر مرتفعة",
      "volatility20Pct": 4.986,
      "maxDrawdown100Pct": 22.599,
      "hardFailureCount": 0,
      "softFailureCount": 0,
      "softFailures": [],
      "chartPath": "../../data/quant/stocks/GIHD.json",
      "latestAlerts": [
        {
          "generatedAt": "2026-07-16T13:06:58.620Z",
          "acknowledged": false,
          "id": "2026-07-16:GIHD:state_change:ENTRY_ZONE",
          "level": "opportunity",
          "type": "state_change",
          "ticker": "GIHD",
          "titleAr": "GIHD: داخل منطقة الدخول",
          "detailAr": "الحالة السابقة: أعلى منطقة الدخول — السعر 50.25.",
          "actionAr": "راجع الشروط والسيولة قبل تسجيل محاكاة ورقية.",
          "previousValue": "ABOVE_ENTRY",
          "currentValue": "ENTRY_ZONE",
          "price": 50.25,
          "tier": "TIER_B_PRIORITY_WATCH"
        },
        {
          "generatedAt": "2026-07-16T13:06:58.620Z",
          "acknowledged": false,
          "id": "2026-07-16:GIHD:tier_change:TIER_A_EXPERIMENTAL_PAPER:TIER_B_PRIORITY_WATCH",
          "level": "opportunity",
          "type": "tier_change",
          "ticker": "GIHD",
          "titleAr": "GIHD: تغير مستوى الترشيح",
          "detailAr": "من الطبقة A — ورقي تجريبي إلى الطبقة B — مراقبة أولوية.",
          "actionAr": "راجع أسباب التغير في صفحة قرار اليوم.",
          "previousValue": "TIER_A_EXPERIMENTAL_PAPER",
          "currentValue": "TIER_B_PRIORITY_WATCH",
          "price": 50.25,
          "tier": "TIER_B_PRIORITY_WATCH"
        },
        {
          "generatedAt": "2026-07-16T13:06:58.620Z",
          "acknowledged": false,
          "id": "2026-07-16:GIHD:decision_score_change:79",
          "level": "warning",
          "type": "decision_score_change",
          "ticker": "GIHD",
          "titleAr": "GIHD: تغير مهم في درجة القرار",
          "detailAr": "من 90.8 إلى 78.7.",
          "actionAr": "راجع أسباب الدرجة؛ ليست احتمال ربح.",
          "previousValue": 90.8,
          "currentValue": 78.7,
          "price": 50.25,
          "tier": "TIER_B_PRIORITY_WATCH"
        },
        {
          "generatedAt": "2026-07-16T09:55:18.611Z",
          "acknowledged": false,
          "id": "2026-07-16:GIHD:snapshot_move:-1:1",
          "level": "warning",
          "type": "snapshot_move",
          "ticker": "GIHD",
          "titleAr": "GIHD: هبوط 2.36% منذ آخر لقطة",
          "detailAr": "السعر السابق 51.7 والحالي 50.48.",
          "actionAr": "راجع الخطة والوقف والحجم قبل أي قرار.",
          "previousValue": 51.7,
          "currentValue": 50.48,
          "price": 50.48,
          "tier": "TIER_A_EXPERIMENTAL_PAPER"
        },
        {
          "generatedAt": "2026-07-16T09:55:18.611Z",
          "acknowledged": false,
          "id": "2026-07-16:GIHD:session_down_cross:-3",
          "level": "warning",
          "type": "session_down_cross",
          "ticker": "GIHD",
          "titleAr": "GIHD: هبط دون -3% خلال الجلسة",
          "detailAr": "التغير الحالي -3.13%.",
          "actionAr": "راجع الدعم والوقف وأوقف أي دخول جديد عند كسر الخطة.",
          "currentValue": -3.13,
          "price": 50.48,
          "tier": "TIER_A_EXPERIMENTAL_PAPER"
        }
      ],
      "sourceMode": "public_delayed",
      "source": "mubasher_symbol_pages",
      "finalDecision": {
        "code": "WATCH_ONLY",
        "labelAr": "مراقبة فقط",
        "actionable": false,
        "reasonAr": "الطبقة B لا تتحول إلى شراء بسبب حركة لحظية."
      },
      "priorityScore": 60.67,
      "riskPct": 0.25,
      "unifiedRank": 26
    },
    {
      "ticker": "MFSC",
      "companyNameAr": "مصر للأسواق الحرة",
      "companyNameEn": "Egypt Free Shops",
      "sector": "غير مصنف",
      "tier": "TIER_B_PRIORITY_WATCH",
      "tierLabelAr": "الطبقة B — مراقبة أولوية",
      "baselineRank": 27,
      "liveRank": 27,
      "rankChange": 0,
      "recommendationScore": 90.4,
      "baselineDecisionScore": 67.6,
      "liveDecisionScore": 62.7,
      "currentPrice": 46.46,
      "changePct": -1.06,
      "moveSincePreviousSnapshotPct": 0,
      "state": "ENTRY_ZONE",
      "stateLabelAr": "داخل منطقة الدخول",
      "fetchedAt": "2026-07-16T14:54:30.475Z",
      "dataAgeMinutes": 1.1,
      "stale": false,
      "marketCurrent": true,
      "plan": {
        "entryLow": 46.1812,
        "entryHigh": 46.8781,
        "stopLoss": 43.9706,
        "target1": 51.1361,
        "target2": 53.1834,
        "riskReward1": 1.8,
        "maximumHoldingSessions": 10
      },
      "support20": 43,
      "resistance20": 53,
      "rsi14": 58.538,
      "volumeRatio20": 1.688,
      "turnover": 0,
      "averageTurnover20Egp": 5290977.184,
      "turnoverPaceRatio": 0,
      "liquidityPercentile": 23.6,
      "riskScore": 73,
      "riskLabelAr": "مخاطر مرتفعة",
      "volatility20Pct": 3.055,
      "maxDrawdown100Pct": 19.561,
      "hardFailureCount": 0,
      "softFailureCount": 0,
      "softFailures": [],
      "chartPath": "../../data/quant/stocks/MFSC.json",
      "latestAlerts": [],
      "sourceMode": "public_delayed",
      "source": "mubasher_symbol_pages",
      "finalDecision": {
        "code": "WATCH_ONLY",
        "labelAr": "مراقبة فقط",
        "actionable": false,
        "reasonAr": "الطبقة B لا تتحول إلى شراء بسبب حركة لحظية."
      },
      "priorityScore": 60.27,
      "riskPct": 0.25,
      "unifiedRank": 27
    }
  ],
  "discoveryWatch": [],
  "allocationPolicy": {
    "strictRiskPct": 0.5,
    "tierARiskPct": 0.25,
    "maximumStockWeightPct": 15,
    "maximumSectorWeightPct": 30,
    "maximumLiquidityParticipationPct": 1
  },
  "warningAr": "هذه الصفحة توحد الطبقات والسعر والخطة والتنبيهات. لا تضمن الربح ولا ترسل أوامر حقيقية."
}
